[
  {
    "is_active": true,
    "ad_archive_id": "1193759999189610",
    "collation_id": "1020480056369192",
    "collation_count": 1,
    "page_id": "425181617530046",
    "page_name": "Lớp Toeic Thầy Long",
    "page_profile_uri": "https://www.facebook.com/ToeicThayLong/",
    "page_profile_picture_url": "https://scontent.fhan14-3.fna.fbcdn.net/v/t39.35426-6/495537488_23987474544178601_6000449820027225490_n.jpg?stp=dst-jpg_s60x60_tt6&_nc_cat=111&ccb=1-7&_nc_sid=c53f8f&_nc_ohc=kBkOFJzLJ1kQ7kNvwEjo6xW&_nc_oc=AdnMWa9nsGJolmvsuf1TCeyB-9lQxLrweIkXkVStE9iCvEGG4VUuFNgDF7D4E-jn5-U&_nc_zt=14&_nc_ht=scontent.fhan14-3.fna&_nc_gid=aHbkyQBIBM_3jnFGNUwwVQ&oh=00_AfTrn_FqFWmuVdJXOxPHClroOjm7PRO2o6cNcZIHUquVFA&oe=687C540E",
    "publisher_platform": [
      "FACEBOOK",
      "INSTAGRAM",
      "AUDIENCE_NETWORK"
    ],
    "display_format": "VIDEO",
    "original_image_urls": [],
    "video_preview_image_url": null,
    "video_sd_url": null,
    "body_text": "🎯 Hành trình chinh phục 360/400 TOEIC Speaking & Writing của Linh Lê!\n\nNgọc Linh – sinh viên Học viện Tài chính – đã xuất sắc ghi dấu ấn với 170/200 điểm Speaking và 190/200 điểm Writing, tổng cộng 360/400 điểm TOEIC S&W – một thành tích đáng ngưỡng mộ! 🌟\n\n✨ Vậy Linh đã học như thế nào để đạt được kết quả này?\nCùng khám phá bí quyết học tập, chiến lược ôn luyện, và nguồn tài liệu chất lượng mà Linh đã áp dụng để “bứt phá” điểm số TOEIC nhé!\n\n📥 Nhắn tin ngay để nhận miễn phí lộ trình học TOEIC 4 kỹ năng – từ cơ bản đến nâng cao, cá nhân hóa theo từng mục tiêu! 🚀\n\n#thaylongtoeic #thaylongreview #TOEICSpeaking #TOEICWriting",
    "cta_text": "Gửi tin nhắn",
    "start_date_readable": "14:00:00 14/07/2025",
    "end_date_readable": "14:00:00 15/07/2025",
    "duration_days": 1
  },
  {
    "is_active": true,
    "ad_archive_id": "1100788251917693",
    "collation_id": "705469829134127",
    "collation_count": 4,
    "page_id": "425181617530046",
    "page_name": "Lớp Toeic Thầy Long",
    "page_profile_uri": "https://www.facebook.com/ToeicThayLong/",
    "page_profile_picture_url": "https://scontent.fhan14-1.fna.fbcdn.net/v/t39.35426-6/518459416_1802065017321122_2199066278924425851_n.jpg?stp=dst-jpg_s60x60_tt6&_nc_cat=105&ccb=1-7&_nc_sid=c53f8f&_nc_ohc=--_NOGbP37wQ7kNvwGIaY00&_nc_oc=AdliOwHfkoMBS7wByVjWOmLQj8vOQPW8MGncLFEjmCGWGd_n9IpGIZb4wjDERqSyiBg&_nc_zt=14&_nc_ht=scontent.fhan14-1.fna&_nc_gid=aHbkyQBIBM_3jnFGNUwwVQ&oh=00_AfSC4D3clMruxPNSamQIxn5Xep1hrYpuWgiAH_5SAavv8A&oe=687C5EBE",
    "publisher_platform": [
      "FACEBOOK",
      "INSTAGRAM",
      "MESSENGER"
    ],
    "display_format": "VIDEO",
    "original_image_urls": [],
    "video_preview_image_url": null,
    "video_sd_url": null,
    "body_text": "Một ngày học tập đầy hiệu quả để đạt được 180/200 TOEIC Speaking sẽ như thế nào?\nCùng lắng nghe Thu Hằng – sinh viên năm 4 Học viện Báo chí & Tuyên truyền – bật mí bí quyết học và luyện nói hiệu quả nhé!\n\nNhắn tin ngay để nhận lộ trình học TOEIC Online – cá nhân hóa theo mục tiêu của bạn!\n#thaylongtoeic #thaylongreview",
    "cta_text": "Gửi tin nhắn",
    "start_date_readable": "14:00:00 13/07/2025",
    "end_date_readable": "14:00:00 14/07/2025",
    "duration_days": 1
  },
  {
    "is_active": true,
    "ad_archive_id": "23920629724293769",
    "collation_id": "705469829134127",
    "collation_count": 0,
    "page_id": "425181617530046",
    "page_name": "Lớp Toeic Thầy Long",
    "page_profile_uri": "https://www.facebook.com/ToeicThayLong/",
    "page_profile_picture_url": "https://scontent.fhan14-2.fna.fbcdn.net/v/t39.35426-6/518181936_601553072893537_8560095764515559921_n.jpg?stp=dst-jpg_s60x60_tt6&_nc_cat=108&ccb=1-7&_nc_sid=c53f8f&_nc_ohc=mPC8_3f2v3cQ7kNvwFcTvlG&_nc_oc=Adkr4u7gtp7yzy6BrzRMIEzh6jcwP-GFZP-8pnuX6Ry_ER9l_skgsX7ymvAuDnMe0Og&_nc_zt=14&_nc_ht=scontent.fhan14-2.fna&_nc_gid=aHbkyQBIBM_3jnFGNUwwVQ&oh=00_AfQoafzDJWun0pRtREH2TG3W-JVXC5bWC4GVEWpu_pVNuA&oe=687C6B63",
    "publisher_platform": [
      "FACEBOOK",
      "MESSENGER"
    ],
    "display_format": "VIDEO",
    "original_image_urls": [],
    "video_preview_image_url": null,
    "video_sd_url": null,
    "body_text": "Một ngày học tập đầy hiệu quả để đạt được 180/200 TOEIC Speaking sẽ như thế nào?\nCùng lắng nghe Thu Hằng – sinh viên năm 4 Học viện Báo chí & Tuyên truyền – bật mí bí quyết học và luyện nói hiệu quả nhé!\n\nNhắn tin ngay để nhận lộ trình học TOEIC Online – cá nhân hóa theo mục tiêu của bạn!\n#thaylongtoeic #thaylongreview",
    "cta_text": "Gửi tin nhắn",
    "start_date_readable": "14:00:00 10/07/2025",
    "end_date_readable": "14:00:00 14/07/2025",
    "duration_days": 4
  },
  {
    "is_active": true,
    "ad_archive_id": "714605584662115",
    "collation_id": "705469829134127",
    "collation_count": 0,
    "page_id": "425181617530046",
    "page_name": "Lớp Toeic Thầy Long",
    "page_profile_uri": "https://www.facebook.com/ToeicThayLong/",
    "page_profile_picture_url": "https://scontent.fhan14-5.fna.fbcdn.net/v/t39.35426-6/518199366_1060640602336967_6088434148278704485_n.jpg?stp=dst-jpg_s60x60_tt6&_nc_cat=104&ccb=1-7&_nc_sid=c53f8f&_nc_ohc=uzsueM9ccbgQ7kNvwFhRJ22&_nc_oc=AdliOjEj9atF_O43rhC_E7U4DfMaZINAz4uMEPAC6ElBPGvmdA3_OesriSAKoHVj08s&_nc_zt=14&_nc_ht=scontent.fhan14-5.fna&_nc_gid=aHbkyQBIBM_3jnFGNUwwVQ&oh=00_AfS-0C080-zTDLf_AmPkSd4ovgKlWeba5hdWOJw4UdF41A&oe=687C8499",
    "publisher_platform": [
      "FACEBOOK",
      "INSTAGRAM",
      "AUDIENCE_NETWORK"
    ],
    "display_format": "VIDEO",
    "original_image_urls": [],
    "video_preview_image_url": null,
    "video_sd_url": null,
    "body_text": "Một ngày học tập đầy hiệu quả để đạt được 180/200 TOEIC Speaking sẽ như thế nào?\nCùng lắng nghe Thu Hằng – sinh viên năm 4 Học viện Báo chí & Tuyên truyền – bật mí bí quyết học và luyện nói hiệu quả nhé!\n\nNhắn tin ngay để nhận lộ trình học TOEIC Online – cá nhân hóa theo mục tiêu của bạn!\n#thaylongtoeic #thaylongreview",
    "cta_text": "Gửi tin nhắn",
    "start_date_readable": "14:00:00 08/07/2025",
    "end_date_readable": "14:00:00 15/07/2025",
    "duration_days": 7
  },
  {
    "is_active": true,
    "ad_archive_id": "743956418179179",
    "collation_id": "705469829134127",
    "collation_count": 0,
    "page_id": "425181617530046",
    "page_name": "Lớp Toeic Thầy Long",
    "page_profile_uri": "https://www.facebook.com/ToeicThayLong/",
    "page_profile_picture_url": "https://scontent.fhan14-2.fna.fbcdn.net/v/t39.35426-6/517721279_1579218943052313_897424072951326026_n.jpg?stp=dst-jpg_s60x60_tt6&_nc_cat=108&ccb=1-7&_nc_sid=c53f8f&_nc_ohc=hATGYq5htc8Q7kNvwGCyoMf&_nc_oc=Adm8YyglJS3FuWayvWqJH4sW8t5GeXdctVjjCTv4X0GhixQB7uwdPG3B43plkm_M5xs&_nc_zt=14&_nc_ht=scontent.fhan14-2.fna&_nc_gid=aHbkyQBIBM_3jnFGNUwwVQ&oh=00_AfRUsC6KTBYXs_3b6NBE34DKUqnCe9VDcNGJo1r6NGG2gA&oe=687C6AE8",
    "publisher_platform": [
      "FACEBOOK",
      "INSTAGRAM",
      "AUDIENCE_NETWORK"
    ],
    "display_format": "VIDEO",
    "original_image_urls": [],
    "video_preview_image_url": null,
    "video_sd_url": null,
    "body_text": "Một ngày học tập đầy hiệu quả để đạt được 180/200 TOEIC Speaking sẽ như thế nào?\nCùng lắng nghe Thu Hằng – sinh viên năm 4 Học viện Báo chí & Tuyên truyền – bật mí bí quyết học và luyện nói hiệu quả nhé!\n\nNhắn tin ngay để nhận lộ trình học TOEIC Online – cá nhân hóa theo mục tiêu của bạn!\n#thaylongtoeic #thaylongreview",
    "cta_text": "Gửi tin nhắn",
    "start_date_readable": "14:00:00 08/07/2025",
    "end_date_readable": "14:00:00 15/07/2025",
    "duration_days": 7
  },
  {
    "is_active": true,
    "ad_archive_id": "751503060670575",
    "collation_id": "2610192235994931",
    "collation_count": 1,
    "page_id": "425181617530046",
    "page_name": "Lớp Toeic Thầy Long",
    "page_profile_uri": "https://www.facebook.com/ToeicThayLong/",
    "page_profile_picture_url": "https://scontent.fhan14-2.fna.fbcdn.net/v/t39.35426-6/518144116_1228169289045832_5292205869060401656_n.jpg?stp=dst-jpg_s60x60_tt6&_nc_cat=100&ccb=1-7&_nc_sid=c53f8f&_nc_ohc=I_LaXvacZhMQ7kNvwHI2A6J&_nc_oc=AdlE_lLZ7cocoXB-qZ4DyprtecQlldTnOkYalrtA0LDdDwYoO6mH24J98jC-leHp_Xs&_nc_zt=14&_nc_ht=scontent.fhan14-2.fna&_nc_gid=aHbkyQBIBM_3jnFGNUwwVQ&oh=00_AfQ9GKMNIWL8pCSrtstOzUAK9sPCIbMlUy1UhAWuwCmKwg&oe=687C5126",
    "publisher_platform": [
      "FACEBOOK",
      "INSTAGRAM"
    ],
    "display_format": "VIDEO",
    "original_image_urls": [],
    "video_preview_image_url": null,
    "video_sd_url": null,
    "body_text": "Chúc mừng chàng trai & cô gái tới từ Đại Học Dược Hà Nội đã hoàn thành xong TOEIC Listening & Reading nhé❤️",
    "cta_text": "Gửi tin nhắn",
    "start_date_readable": "14:00:00 12/07/2025",
    "end_date_readable": "14:00:00 15/07/2025",
    "duration_days": 3
  },
  {
    "is_active": true,
    "ad_archive_id": "705020969030554",
    "collation_id": "725693183131496",
    "collation_count": 2,
    "page_id": "425181617530046",
    "page_name": "Lớp Toeic Thầy Long",
    "page_profile_uri": "https://www.facebook.com/ToeicThayLong/",
    "page_profile_picture_url": "https://scontent.fhan14-5.fna.fbcdn.net/v/t39.35426-6/499924089_1189158892532774_8679105973474778879_n.jpg?stp=dst-jpg_s60x60_tt6&_nc_cat=106&ccb=1-7&_nc_sid=c53f8f&_nc_ohc=Hn_ff-kADBAQ7kNvwFRVVF7&_nc_oc=Adll202gkawTiAYHdILVuCjrbVljLhaIls14ZgWG-5VtO0ju1KFb_HrVVKmUbH2MWco&_nc_zt=14&_nc_ht=scontent.fhan14-5.fna&_nc_gid=aHbkyQBIBM_3jnFGNUwwVQ&oh=00_AfTkCLzCmBoZaCL3rdbwXvfOdXc9xKjsqgPP07ubTY9BZA&oe=687C6847",
    "publisher_platform": [
      "FACEBOOK",
      "INSTAGRAM",
      "AUDIENCE_NETWORK"
    ],
    "display_format": "VIDEO",
    "original_image_urls": [],
    "video_preview_image_url": null,
    "video_sd_url": null,
    "body_text": "🧑‍💻 MẠNH TOÀN – sinh viên Kỹ thuật phần mềm trường Đại Học FPT, vừa chinh phục số điểm 845/990 sau khóa TOEIC Online A216.\n📖 Từ chỗ phải tra từng dòng tài liệu, đến nay Toàn đã tự tin đọc hiểu 80-90% nội dung trên StackOverflow, xem video và hiểu tới 80% video hướng dẫn lập trình.\n\n👉 Nếu bạn cũng đang loay hoay với tiếng Anh chuyên ngành, hãy bắt đầu từ nền tảng vững chắc như Toàn nhé! Một khi đã giỏi tiếng Anh, lập trình trở nên dễ dàng hơn rất nhiều!\n\n📥 Nhắn tin ngay để nhận miễn phí lộ trình học TOEIC 4 kỹ năng – từ cơ bản đến nâng cao, cá nhân hóa theo từng mục tiêu! 🚀\n\n#TOEICOnline #TOEIC #thaylongtoeic",
    "cta_text": "Gửi tin nhắn",
    "start_date_readable": "14:00:00 12/07/2025",
    "end_date_readable": "14:00:00 15/07/2025",
    "duration_days": 3
  },
  {
    "is_active": true,
    "ad_archive_id": "760253119999983",
    "collation_id": "1082270087173480",
    "collation_count": 1,
    "page_id": "425181617530046",
    "page_name": "Lớp Toeic Thầy Long",
    "page_profile_uri": "https://www.facebook.com/ToeicThayLong/",
    "page_profile_picture_url": "https://scontent.fhan14-4.fna.fbcdn.net/v/t39.35426-6/517611755_1155334433099665_5959875175949296736_n.jpg?stp=dst-jpg_s60x60_tt6&_nc_cat=102&ccb=1-7&_nc_sid=c53f8f&_nc_ohc=O4Zcy0O6w2oQ7kNvwEGqNNf&_nc_oc=Adn6gQhGrIzoOd2kjin0V0b8MD1aItn05qFPzcDZ5MwGof2kImxCJHyM-HCUoK8R6Gw&_nc_zt=14&_nc_ht=scontent.fhan14-4.fna&_nc_gid=aHbkyQBIBM_3jnFGNUwwVQ&oh=00_AfRXFZfywcBIz5bcht6OgGBzNqyyoFu0f13t7r5WFIHEkw&oe=687C887D",
    "publisher_platform": [
      "FACEBOOK",
      "INSTAGRAM",
      "AUDIENCE_NETWORK"
    ],
    "display_format": "MULTI_IMAGES",
    "original_image_urls": [
      "https://scontent.fhan14-2.fna.fbcdn.net/v/t39.35426-6/518307147_1737258190493290_8871473819085072800_n.jpg?_nc_cat=108&ccb=1-7&_nc_sid=c53f8f&_nc_ohc=6bcAmtTfk0cQ7kNvwGsELeJ&_nc_oc=AdlaJ9OGnjbrwprXCDl31s2B9ZeULqmZf33ne1NuvUj3bXsWxa7On445609hq__OA4I&_nc_zt=14&_nc_ht=scontent.fhan14-2.fna&_nc_gid=aHbkyQBIBM_3jnFGNUwwVQ&oh=00_AfSxcTOH9bwJGmrok-ttGq-ilMEKm4TwfWh9Jdo4d5Y7ag&oe=687C6B1E",
      "https://scontent.fhan14-5.fna.fbcdn.net/v/t39.35426-6/517865379_774164211701033_2517717895452390881_n.jpg?_nc_cat=106&ccb=1-7&_nc_sid=c53f8f&_nc_ohc=yPITc2YW-wUQ7kNvwHf5hsl&_nc_oc=Adno2xVgzv3p6TMyddK-yeddaNYYB4SO6-RZj67ZrqMR4MZP0E30v0dWR-Wxl_7t8ZA&_nc_zt=14&_nc_ht=scontent.fhan14-5.fna&_nc_gid=aHbkyQBIBM_3jnFGNUwwVQ&oh=00_AfSKOlJeL2C9ex1ONaPfKfMmc7l4zKnPJ2IxwFAZ0onL_w&oe=687C7D42",
      "https://scontent.fhan14-1.fna.fbcdn.net/v/t39.35426-6/517222111_1046487347634678_7258504044957999696_n.jpg?_nc_cat=105&ccb=1-7&_nc_sid=c53f8f&_nc_ohc=qGlbOWNHGeoQ7kNvwEWozvX&_nc_oc=AdmyxFT-CRBKo-kznRO4dDzpc4lgHNMUX1PKlIbFC1Q5-gDmUCEksIk2OIGd0psRoIg&_nc_zt=14&_nc_ht=scontent.fhan14-1.fna&_nc_gid=aHbkyQBIBM_3jnFGNUwwVQ&oh=00_AfSgzhppNDGqR72_x_GG2r8BvP2eOIzkugkijI-rqk9kSg&oe=687C5A0B",
      "https://scontent.fhan14-4.fna.fbcdn.net/v/t39.35426-6/517155242_794595076237966_8913618468000946818_n.jpg?_nc_cat=107&ccb=1-7&_nc_sid=c53f8f&_nc_ohc=M9DbPKnuKmIQ7kNvwGs121G&_nc_oc=Adk5IDzDiRm8a2ktwrN7fVksMQoeXx0cxTxLFgX_nBQUjuSR82RVKbSIKObYWkEVTKk&_nc_zt=14&_nc_ht=scontent.fhan14-4.fna&_nc_gid=aHbkyQBIBM_3jnFGNUwwVQ&oh=00_AfR2zVFjRF7UePhkcUTdgbWCZWs4_DZPSYceAYDNE2hq2Q&oe=687C792B",
      "https://scontent.fhan14-5.fna.fbcdn.net/v/t39.35426-6/518302224_1063129992590722_2866891050381267320_n.jpg?_nc_cat=109&ccb=1-7&_nc_sid=c53f8f&_nc_ohc=JK3HCWP_OuUQ7kNvwEikRKM&_nc_oc=AdnKTnyxKqgPsLSfeB1ksHSfF0nSdwbK2Pui_0PQA6iwbtCCOwcbyR5ajmy5FVvZL_U&_nc_zt=14&_nc_ht=scontent.fhan14-5.fna&_nc_gid=aHbkyQBIBM_3jnFGNUwwVQ&oh=00_AfQ2U1za7xh5NfUfKecw281ngXkO4Vyi54GxwimgqiQQcA&oe=687C71A6",
      "https://scontent.fhan14-2.fna.fbcdn.net/v/t39.35426-6/517173317_1226368275957984_8155000159104348144_n.jpg?_nc_cat=100&ccb=1-7&_nc_sid=c53f8f&_nc_ohc=SsykHanPluQQ7kNvwE1ThBe&_nc_oc=AdkEbi3oYH6S8jYJqBpsxOt-ohJ1hiL4ZUdHvB1dCUlffaxGQLjj1-DDkwQ4EMIjfiA&_nc_zt=14&_nc_ht=scontent.fhan14-2.fna&_nc_gid=aHbkyQBIBM_3jnFGNUwwVQ&oh=00_AfRDn7E8VAYxNlSib07aoj__Xjjw4uRjCOyvC8Qp-avvYw&oe=687C557E",
      "https://scontent.fhan14-1.fna.fbcdn.net/v/t39.35426-6/515986155_1773554740192576_5733547411150638328_n.jpg?_nc_cat=105&ccb=1-7&_nc_sid=c53f8f&_nc_ohc=ecGQdZ4hNTkQ7kNvwEop02k&_nc_oc=AdkJ9omorvscF7XXAv74yG9sI7YJO4LgehJ3cs9TIqKfjxMKOvy_Do5R9JE5HGbahq8&_nc_zt=14&_nc_ht=scontent.fhan14-1.fna&_nc_gid=aHbkyQBIBM_3jnFGNUwwVQ&oh=00_AfTw7nfPPkxx4HK2PHVtw2Tvjr8NwCVZ12uDA9dsOJNWbw&oe=687C59E1",
      "https://scontent.fhan14-5.fna.fbcdn.net/v/t39.35426-6/517352628_756899203421730_410881195270165305_n.jpg?_nc_cat=104&ccb=1-7&_nc_sid=c53f8f&_nc_ohc=qqybaSQkR2cQ7kNvwFx2paQ&_nc_oc=AdnbTW-8LbDP6hZzh7P2H_Vqi1vyLMxJ4yRyn2P523vaOCayKlYaN-GIrWXLM7JtBno&_nc_zt=14&_nc_ht=scontent.fhan14-5.fna&_nc_gid=aHbkyQBIBM_3jnFGNUwwVQ&oh=00_AfQBHdsBfKh_avpiAtMawcwufeCTZ1QrQmgXxZYELzTkIg&oe=687C6745",
      "https://scontent.fhan14-5.fna.fbcdn.net/v/t39.35426-6/516703249_4123034854634994_7196715312519448506_n.jpg?_nc_cat=109&ccb=1-7&_nc_sid=c53f8f&_nc_ohc=VHCkSXQW1LEQ7kNvwFfVWY9&_nc_oc=AdmGjr5B8xa0WBTFvR79LAUtE5usB-uOpiGKsf0j0TwwijNENNmnlrnTiUyNVG6Ce9A&_nc_zt=14&_nc_ht=scontent.fhan14-5.fna&_nc_gid=aHbkyQBIBM_3jnFGNUwwVQ&oh=00_AfSxEAJH1R6a-z6BSYpAuqYJmC-vqzbbGxAAqXNXCy-QwA&oe=687C60AA",
      "https://scontent.fhan14-3.fna.fbcdn.net/v/t39.35426-6/518482606_1304020067750951_4812983345014513554_n.jpg?_nc_cat=110&ccb=1-7&_nc_sid=c53f8f&_nc_ohc=zL7cbMyomDAQ7kNvwEaDULk&_nc_oc=AdlsJe-x0BDhu9PAsZiCc3AmJN4bHfFzla9b4hz6wVXZ2dgaD0f_S-j9aNV6TTz7RgY&_nc_zt=14&_nc_ht=scontent.fhan14-3.fna&_nc_gid=aHbkyQBIBM_3jnFGNUwwVQ&oh=00_AfT2YXS07TU2JlZPXWFEf7EM95ulsRbGeOMsbueF_BzwHQ&oe=687C7AE4",
      "https://scontent.fhan14-5.fna.fbcdn.net/v/t39.35426-6/517983111_1964486964387498_4886855373555535132_n.jpg?_nc_cat=106&ccb=1-7&_nc_sid=c53f8f&_nc_ohc=iCJlldo2f34Q7kNvwFcJCj3&_nc_oc=AdnvZEm0aY2IOQ7G_Asd2hhneSF6LGp7qGSIhw06gDs-8qs0jM54uYdBDPIRh_qs4ms&_nc_zt=14&_nc_ht=scontent.fhan14-5.fna&_nc_gid=aHbkyQBIBM_3jnFGNUwwVQ&oh=00_AfSvaO_RYh_9Cy-RzcM2jaBU0ZFHYPpaC3u1bufXeumRsQ&oe=687C792C",
      "https://scontent.fhan14-3.fna.fbcdn.net/v/t39.35426-6/518054808_2222056758245078_5511560375052470703_n.jpg?_nc_cat=110&ccb=1-7&_nc_sid=c53f8f&_nc_ohc=yWIiNZKvfFQQ7kNvwGWRVya&_nc_oc=AdnU9dkWp5YfZSQSchwjZ-m_MpBtxDI6rpq4nj3NfduErX7F_4pJBMThqVZNTSGWZFY&_nc_zt=14&_nc_ht=scontent.fhan14-3.fna&_nc_gid=aHbkyQBIBM_3jnFGNUwwVQ&oh=00_AfRD4mhWH8hvzzsRttznha23w8viQD5MUtFOx3xuiFErVw&oe=687C59FF",
      "https://scontent.fhan14-4.fna.fbcdn.net/v/t39.35426-6/518316058_1230392918885258_7071578714749074013_n.jpg?_nc_cat=107&ccb=1-7&_nc_sid=c53f8f&_nc_ohc=hKnnNi3D8pMQ7kNvwETCVOt&_nc_oc=AdmOP3CHsNHUL3kAH9BcGgnfiHJjhR6pUBi5NHdox5OhE8AMGPm8W9h7MO3k4xoxlWk&_nc_zt=14&_nc_ht=scontent.fhan14-4.fna&_nc_gid=aHbkyQBIBM_3jnFGNUwwVQ&oh=00_AfRUGpybFKN5_XLiKm2PEfPZgFrSuXi0GMuJpugSmZenJg&oe=687C804E",
      "https://scontent.fhan14-4.fna.fbcdn.net/v/t39.35426-6/518828945_1518533962455960_1147880974896341677_n.jpg?_nc_cat=107&ccb=1-7&_nc_sid=c53f8f&_nc_ohc=Sl4lLpmaimAQ7kNvwG_Z2I1&_nc_oc=AdkV58gnCVtHDCEYb6uAW9h-KXMb-_MfGkfzMrzW3uK84pTHbFleJeeg-okSceHGAy8&_nc_zt=14&_nc_ht=scontent.fhan14-4.fna&_nc_gid=aHbkyQBIBM_3jnFGNUwwVQ&oh=00_AfQD560qw5asT5m6ioBJF6YOmnk2HAc00z2YWid6RPxxDw&oe=687C891E",
      "https://scontent.fhan14-5.fna.fbcdn.net/v/t39.35426-6/516926404_1081917966727769_1209722379175128970_n.jpg?_nc_cat=106&ccb=1-7&_nc_sid=c53f8f&_nc_ohc=E-K1D-U4GkYQ7kNvwFbhsv8&_nc_oc=AdnfCNJ8JGWCEa7yyEXFsd-G5NT_p7NIHEF-U66gO5RstnU8VYV_AYq7icPUIbfCcHY&_nc_zt=14&_nc_ht=scontent.fhan14-5.fna&_nc_gid=aHbkyQBIBM_3jnFGNUwwVQ&oh=00_AfQC6PYCk51nI7I2bUT3UbIVJn29DbAcSuo1SVhencmmmg&oe=687C5ECD",
      "https://scontent.fhan14-1.fna.fbcdn.net/v/t39.35426-6/518799888_971071615035845_7668350340198071658_n.jpg?_nc_cat=101&ccb=1-7&_nc_sid=c53f8f&_nc_ohc=N-wM4hGexoQQ7kNvwGMWhjS&_nc_oc=AdnDHyYgF0vz3-l5Up0DuUD-M9-x_RRordo94foWAppnNeMWQp5_jZIX-wMPxbtfvE4&_nc_zt=14&_nc_ht=scontent.fhan14-1.fna&_nc_gid=aHbkyQBIBM_3jnFGNUwwVQ&oh=00_AfQgLbl7HAuNE-6pn9WJwN2Lfi52D1uEINzxAm44D0kNiw&oe=687C732D",
      "https://scontent.fhan14-5.fna.fbcdn.net/v/t39.35426-6/517055194_2157984774704807_247777761536152671_n.jpg?_nc_cat=106&ccb=1-7&_nc_sid=c53f8f&_nc_ohc=nzSRgKxRx3IQ7kNvwEvv21e&_nc_oc=Adm9t8vmWFRSaLahmiRqXKYwhkObTXqklWTV86jNxPrxfUHfnXPgHL7VjCzaank80vM&_nc_zt=14&_nc_ht=scontent.fhan14-5.fna&_nc_gid=aHbkyQBIBM_3jnFGNUwwVQ&oh=00_AfQGNaQf15PX9WzODWsVo4dPI4vqOJ4tzJkY2VuTRKFcGA&oe=687C59FC",
      "https://scontent.fhan14-3.fna.fbcdn.net/v/t39.35426-6/517261994_1414252266514056_7293501216104820071_n.jpg?_nc_cat=110&ccb=1-7&_nc_sid=c53f8f&_nc_ohc=vW-8lF23zkcQ7kNvwGz4VUt&_nc_oc=Admi5mfdiPtD2P8dhv4f4hCEXjytwRD6Lh3TQKwgf24Twqn08TY_OAJlSS-CSW_bYO4&_nc_zt=14&_nc_ht=scontent.fhan14-3.fna&_nc_gid=aHbkyQBIBM_3jnFGNUwwVQ&oh=00_AfT9Rc8cE39_IlMeNQlRPtNUKoj0D-CY_7Ia2FWWyCz1qA&oe=687C69E9",
      "https://scontent.fhan14-1.fna.fbcdn.net/v/t39.35426-6/518136242_1255579686065457_998546875934664693_n.jpg?_nc_cat=101&ccb=1-7&_nc_sid=c53f8f&_nc_ohc=GZSHhqXJFC4Q7kNvwGL-3eA&_nc_oc=AdnsKcKXSJ3a1Y3z9VZgzgvZUxEfcF0Mu__zZbe1zLu1w8DbHrRt9u44mr3cNB-SXdY&_nc_zt=14&_nc_ht=scontent.fhan14-1.fna&_nc_gid=aHbkyQBIBM_3jnFGNUwwVQ&oh=00_AfSJwl0E2uusk99Y1DJxz_RdhoDZiwuRrILmKGYusGz8pA&oe=687C76CB",
      "https://scontent.fhan14-3.fna.fbcdn.net/v/t39.35426-6/517159589_1179365120893474_2466290769545861084_n.jpg?_nc_cat=111&ccb=1-7&_nc_sid=c53f8f&_nc_ohc=sHFu4npf5tYQ7kNvwHfv0An&_nc_oc=AdkrARgQaDPM2foTyKVpi_03SzcyYi1bfNz70szWfRSIUhAzP46mhP4xiFHX60lN2Lw&_nc_zt=14&_nc_ht=scontent.fhan14-3.fna&_nc_gid=aHbkyQBIBM_3jnFGNUwwVQ&oh=00_AfSjxlDcb1B2P8kXJZWenzFkU_rmM70S7ebuqHOJeaYVMQ&oe=687C758B",
      "https://scontent.fhan14-2.fna.fbcdn.net/v/t39.35426-6/516359788_1362245308204248_2209382597867606227_n.jpg?_nc_cat=108&ccb=1-7&_nc_sid=c53f8f&_nc_ohc=RE_szJYZTFAQ7kNvwGR3EBm&_nc_oc=Adlg7hBP-Fbo_49h19G_tQ1Y5P6Ok3mltdA9A3aBekYOQmnvsxUz99UKMrtg98L_rXg&_nc_zt=14&_nc_ht=scontent.fhan14-2.fna&_nc_gid=aHbkyQBIBM_3jnFGNUwwVQ&oh=00_AfQtqglJkmYcKRlzgo57kFAz3vX4A10ZwI23w9s0agwqJw&oe=687C78A8",
      "https://scontent.fhan14-5.fna.fbcdn.net/v/t39.35426-6/517770834_670974025977245_7244669875821625308_n.jpg?_nc_cat=109&ccb=1-7&_nc_sid=c53f8f&_nc_ohc=vwWNkX71tFkQ7kNvwG5BISd&_nc_oc=Adk4liNXcRGvhcvulHVqkKswhk7PJY_mOD-3dxvRWNQ4dgbIYihIwOGPZaC9Uk_bk2I&_nc_zt=14&_nc_ht=scontent.fhan14-5.fna&_nc_gid=aHbkyQBIBM_3jnFGNUwwVQ&oh=00_AfS6mPrrMc1U1VBs3zH48Ck90DFi8tY-FmoBSoGdqdTFDw&oe=687C59CC",
      "https://scontent.fhan14-5.fna.fbcdn.net/v/t39.35426-6/516603953_2884063058444028_6604401684891064097_n.jpg?_nc_cat=109&ccb=1-7&_nc_sid=c53f8f&_nc_ohc=VkSeCcyZfasQ7kNvwEU5GO-&_nc_oc=AdneL7IvSTMo6Bph3GamAbEw7H3ZA_MLHuK08mFBegBpiqNAaH0f8bwyic3P8PdEOZ0&_nc_zt=14&_nc_ht=scontent.fhan14-5.fna&_nc_gid=aHbkyQBIBM_3jnFGNUwwVQ&oh=00_AfSE6WPzjJt4kkHnx7XgFtJpmwoWDrH0576wwSB_Go9RJQ&oe=687C7872",
      "https://scontent.fhan14-5.fna.fbcdn.net/v/t39.35426-6/517552863_2219167485199954_3224120830119633235_n.jpg?_nc_cat=106&ccb=1-7&_nc_sid=c53f8f&_nc_ohc=VIw0gfSbDKgQ7kNvwEUZ7Z5&_nc_oc=AdlZm3oUk5Iyz3XpJQ6TeF0FADFTibZkUnIQRRcgRt7T_RYQFSbkyMTxT18GAPV2qyQ&_nc_zt=14&_nc_ht=scontent.fhan14-5.fna&_nc_gid=aHbkyQBIBM_3jnFGNUwwVQ&oh=00_AfQDyN6jMkpN3Ss01H3CJktMfa8xMaIkssDcONfed-ualg&oe=687C83A6",
      "https://scontent.fhan14-2.fna.fbcdn.net/v/t39.35426-6/517582848_1449188736534099_4211788576453722725_n.jpg?_nc_cat=100&ccb=1-7&_nc_sid=c53f8f&_nc_ohc=rs-k_ynd4_oQ7kNvwFY1Lwf&_nc_oc=AdldNCd7oH7lPjBaJMAHKwR2--pkvww686La6HvJhxfkooUy4_7t9vOCCMZ7CFJsC_8&_nc_zt=14&_nc_ht=scontent.fhan14-2.fna&_nc_gid=aHbkyQBIBM_3jnFGNUwwVQ&oh=00_AfSi3ybu-F1miAM8U-yQwXVqQxmHUgI1GFmIFz2rj2foeA&oe=687C8256",
      "https://scontent.fhan14-1.fna.fbcdn.net/v/t39.35426-6/517399622_740852545547094_5702391357635975184_n.jpg?_nc_cat=105&ccb=1-7&_nc_sid=c53f8f&_nc_ohc=pE1SSIL5WpEQ7kNvwHIm_z1&_nc_oc=Adn67e-BsHLGcAl4C-boAIMsPPHcSllGwnU5FirJahD7OFPVTMqG2Wn7D8KH7O9MXDo&_nc_zt=14&_nc_ht=scontent.fhan14-1.fna&_nc_gid=aHbkyQBIBM_3jnFGNUwwVQ&oh=00_AfRipWbiaKEXwzBz7zltOjMbrX3f4jAtzpjSedsdj3qh4g&oe=687C683D",
      "https://scontent.fhan14-1.fna.fbcdn.net/v/t39.35426-6/517408733_714078784876769_6208389287708419219_n.jpg?_nc_cat=101&ccb=1-7&_nc_sid=c53f8f&_nc_ohc=JHTWTy3jF3cQ7kNvwFBYn1G&_nc_oc=AdlSmcjDhCEJr9-0Kp2Yvk902T3FALNV9RD52yG8nAKuttLTXHxEt4e822Uz3sEBIHE&_nc_zt=14&_nc_ht=scontent.fhan14-1.fna&_nc_gid=aHbkyQBIBM_3jnFGNUwwVQ&oh=00_AfQYghwqvGmN9ZCywerKTHmXfPUYwPL7omShoSjQbxJ3uw&oe=687C6688",
      "https://scontent.fhan14-5.fna.fbcdn.net/v/t39.35426-6/517393083_1450327742666015_994996456580122910_n.jpg?_nc_cat=104&ccb=1-7&_nc_sid=c53f8f&_nc_ohc=RvjxU9U45S4Q7kNvwH1rnB3&_nc_oc=AdnHIDjcmVlfPDBRFc6RFDPnHzz4joIy_AwKw5lAMiicjD0YXFFkd8YDeJcaxS_ajuE&_nc_zt=14&_nc_ht=scontent.fhan14-5.fna&_nc_gid=aHbkyQBIBM_3jnFGNUwwVQ&oh=00_AfRpy3aTRzjNx8b88u0XVYw_4mY2VymU42sm9e5dqBRKHA&oe=687C7472",
      "https://scontent.fhan14-3.fna.fbcdn.net/v/t39.35426-6/517634916_776638221596991_8709766373775722253_n.jpg?_nc_cat=111&ccb=1-7&_nc_sid=c53f8f&_nc_ohc=vWQnJy5Is4gQ7kNvwGc0pE8&_nc_oc=Adkl_VyKUItZncBulCd6E0X9PJCIYi4TNMLvmpRcjNTlCZVzynkph-20OU9TxmEE-c8&_nc_zt=14&_nc_ht=scontent.fhan14-3.fna&_nc_gid=aHbkyQBIBM_3jnFGNUwwVQ&oh=00_AfS59pK59Vxhiu_Q2EWpKc9HQMOG1agTu7KNRlEZkEk12A&oe=687C7C18",
      "https://scontent.fhan14-2.fna.fbcdn.net/v/t39.35426-6/518242487_705325855732219_6884112109431922486_n.jpg?_nc_cat=100&ccb=1-7&_nc_sid=c53f8f&_nc_ohc=4iwXK70BAHUQ7kNvwFalt4o&_nc_oc=AdkFmsuf-mBRXDVuTS-2xyUZmFTqcoRxhrwomViEBGdrkm-pUUeGyqF5xVAU-mG4EZA&_nc_zt=14&_nc_ht=scontent.fhan14-2.fna&_nc_gid=aHbkyQBIBM_3jnFGNUwwVQ&oh=00_AfSCcOZ8KYhLcFDn4aERxHZujQKJ9YMokYx6ui4ePU4P_w&oe=687C66A8",
      "https://scontent.fhan14-2.fna.fbcdn.net/v/t39.35426-6/518252211_24157818570480730_2978592058640547516_n.jpg?_nc_cat=108&ccb=1-7&_nc_sid=c53f8f&_nc_ohc=_57Z93uP8SwQ7kNvwG_3pwP&_nc_oc=AdnQCYdsLYjU6Oc9eLfurcPZaoHlkbd-vnjyFvxxwGbvxYnsk9VNHEK0WWD6yDL_GL4&_nc_zt=14&_nc_ht=scontent.fhan14-2.fna&_nc_gid=aHbkyQBIBM_3jnFGNUwwVQ&oh=00_AfT6GZxGJa44mLLiuUddFxEMw28U6h92uv2PYuZ57vfn4g&oe=687C769E",
      "https://scontent.fhan14-2.fna.fbcdn.net/v/t39.35426-6/517350108_1123823429582518_5233852219456383654_n.jpg?_nc_cat=108&ccb=1-7&_nc_sid=c53f8f&_nc_ohc=g_mhFKHFl88Q7kNvwG5gzKR&_nc_oc=Adn7RQzVoUgPAEVcwfNdxJG_ChHa3Aynr683WTOWM-FG4ChucCQom3kmPiiMlcdVT8s&_nc_zt=14&_nc_ht=scontent.fhan14-2.fna&_nc_gid=aHbkyQBIBM_3jnFGNUwwVQ&oh=00_AfSAXiTyJMUgge8fx1_UbLI9LnMfKUykH4UkwxSwiwqIzw&oe=687C5B0E",
      "https://scontent.fhan14-1.fna.fbcdn.net/v/t39.35426-6/518003994_1148531407083651_6751097021969672670_n.jpg?_nc_cat=101&ccb=1-7&_nc_sid=c53f8f&_nc_ohc=GC5qtHThAd0Q7kNvwGZGfzR&_nc_oc=Adna44WnTYW0ne6Um3h1bVN3fQ8oFy7F3CCNl4M5BzHLEpP3YFoXjw_VR1GO5Z7hSqw&_nc_zt=14&_nc_ht=scontent.fhan14-1.fna&_nc_gid=aHbkyQBIBM_3jnFGNUwwVQ&oh=00_AfQz8AawTYu4m8VO0cUgnd5M-gT5HMdsInvf_X-EFHAZKA&oe=687C537D",
      "https://scontent.fhan14-1.fna.fbcdn.net/v/t39.35426-6/517371258_1248267680335088_7239296071064357413_n.jpg?_nc_cat=101&ccb=1-7&_nc_sid=c53f8f&_nc_ohc=qcFJLVnrPLQQ7kNvwFzjhWy&_nc_oc=Adkdqqkizi55GRUNLP9kdvDmJyN6PTFeuMLrQZBTbJx4-qSIBkuvwkFOuot4jQ8wYFg&_nc_zt=14&_nc_ht=scontent.fhan14-1.fna&_nc_gid=aHbkyQBIBM_3jnFGNUwwVQ&oh=00_AfSA9HqR6FIVlCM-xUxHdbH1EvMjlkRtn5T_y_eCsKKRGQ&oe=687C6EDF",
      "https://scontent.fhan14-2.fna.fbcdn.net/v/t39.35426-6/518311225_1390172878758410_831882039347525230_n.jpg?_nc_cat=108&ccb=1-7&_nc_sid=c53f8f&_nc_ohc=7GBkWoJSPtMQ7kNvwGu7Vjk&_nc_oc=AdkhcpAPC8etpjhjtIsz2HFquFDHMC4OXZr9QLYUTXK-qKZ455W-x7X3gCpSgpjGyWo&_nc_zt=14&_nc_ht=scontent.fhan14-2.fna&_nc_gid=aHbkyQBIBM_3jnFGNUwwVQ&oh=00_AfRPEkziCX6dRkZNAwQFcH9tvLBbf3T08rkzb681886YuA&oe=687C718F"
    ],
    "video_preview_image_url": null,
    "video_sd_url": null,
    "body_text": "Thêm những bảng điểm TOEIC 4 kỹ năng mới siu chất \nCảm ơn các em đã luôn tin tưởng và lựa chọn Lớp TOEIC thầy Long\n🥰🥰 👏👏👏",
    "cta_text": "Gửi tin nhắn",
    "start_date_readable": "14:00:00 11/07/2025",
    "end_date_readable": "14:00:00 15/07/2025",
    "duration_days": 4
  },
  {
    "is_active": true,
    "ad_archive_id": "23937349795959767",
    "collation_id": "2226531191134383",
    "collation_count": 2,
    "page_id": "425181617530046",
    "page_name": "Lớp Toeic Thầy Long",
    "page_profile_uri": "https://www.facebook.com/ToeicThayLong/",
    "page_profile_picture_url": "https://scontent.fhan14-1.fna.fbcdn.net/v/t39.35426-6/518329866_24076325285360635_2184764976460110759_n.jpg?stp=dst-jpg_s60x60_tt6&_nc_cat=101&ccb=1-7&_nc_sid=c53f8f&_nc_ohc=0j4-jj2TvlMQ7kNvwHTLzoA&_nc_oc=AdlZWsLxYzsFd3p2vjh7mJDYlzgSIouC8R-pVssuMr8wjoQpppv112Xi6aM1EDgA1pM&_nc_zt=14&_nc_ht=scontent.fhan14-1.fna&_nc_gid=aHbkyQBIBM_3jnFGNUwwVQ&oh=00_AfTMZQtkumBInSN_iQaxSsWtIib-X0_l66pc52ZDuuCR3A&oe=687C7570",
    "publisher_platform": [
      "FACEBOOK",
      "INSTAGRAM"
    ],
    "display_format": "IMAGE",
    "original_image_urls": [
      "https://scontent.fhan14-3.fna.fbcdn.net/v/t39.35426-6/518335734_3978765729101137_4973181746804337638_n.jpg?_nc_cat=103&ccb=1-7&_nc_sid=c53f8f&_nc_ohc=YPv56nKdmxoQ7kNvwHKmeni&_nc_oc=Adk-z1PDLWg0rVzCP9rLbqTze5uID2cRY6Wfv8s_ULttnjkCU5u0ccH7u9jRv43czHI&_nc_zt=14&_nc_ht=scontent.fhan14-3.fna&_nc_gid=aHbkyQBIBM_3jnFGNUwwVQ&oh=00_AfREgeSJcd130LTwKBzBRMRMONVPGidxnwb_ue36ug70PA&oe=687C69F5"
    ],
    "video_preview_image_url": null,
    "video_sd_url": null,
    "body_text": "📆 LỊCH KHAI GIẢNG MỚI NHẤT THÁNG 8-2025\n👉 Đừng bỏ lỡ những lịch học TOEIC 4 kỹ năng mới nhất tháng 8-2025 tại Lớp TOEIC Thầy Long\nXem lịch khai giảng gần nhất tại:\nhttps://thaylongtoeic.com/lich-khai-giang/\n————————————\n👉 THÔNG TIN LỚP HỌC:\n✅ Lớp Tập Sự: Dành cho các bạn mất gốc hoặc mới bắt đầu tiếng Anh\n⚬ Học phí gốc 3.200.000đ/22b + 6b bổ trợ âm Online\n⚬ Phát triển kỹ năng nghe cơ bản.\n⚬ Tích lũy từ vựng tiếng Anh đa chủ đề.\n⚬ Xây dựng khung ngữ pháp cơ bản.\n🎁 Ưu đãi của riêng lớp học\n⚬ Miễn phí tài liệu ôn tập và có website luyện đề giống thi thật tới 90%.\n⚬ Ưu đãi cho đăng ký và hoàn thành học phí sớm giảm còn 3.000.000đ.( áp dụng cho đăng ký và hoàn thành học phí trước khai giảng)\n✅ Lớp TOEIC A: KHOÁ LUYỆN THI DÀNH CHO CÁC BẠN ĐÃ CÓ NỀN TẢNG\n⚬ Học phí gốc 3.900.000 (27 buổi học trực tiếp trên lớp~ 2 tháng 1 tuần).\n⚬ Học phí gốc lớp Online được hưởng ưu đãi giảm 200.000đ chỉ còn 3.700.000đ.\n⚬ Đăng ký và hoàn thành học phí trước khai giảng được giảm còn 3.500.000đ với lớp trực tiếp và 3.300.000đ với lớp Online.\n⚬ Hoàn thành toàn bộ phần nghe trong bài thi TOEIC (Part 1-2-3-4).\n⚬ Hệ thống lại ngữ pháp chủ điểm.\n⚬ Làm quen với phần Reading trong bài thi Toeic.\n⚬ Sỹ số lớp học chỉ từ 23-25 học viên, giáo viên có thể sát sao như trải nghiệm học 1-1\n🎁 Ưu đãi của riêng lớp học\n⚬ Được cung cấp tài liệu miễn phí trong toàn bộ khoá học.\n⚬ Website luyện đề giống thi thật tới 90%, hơn 50 đề thi sát nhất với đề thi thật.\n⚬ Lớp Online được nhận file mềm giáo trình và được thầy cô hỗ trợ trong suốt khóa học.\n✅ Lớp TOEIC Speaking & Writing​​: Dành cho các bạn sau khi hoàn thành kỳ thi TOEIC Listening & Reading muốn nâng cao khả năng nói và viết trong môi trường làm việc quốc tế. Ngoài ra một số trường yêu cầu TOEIC 4 kỹ năng thì các em có thể tham gia nốt khóa học này để hoàn thiện và lấy chứng chỉ TOEIC SW.\n————————————\n🎁 ƯU ĐÃI KHÁC VÀ HỖ TRỢ THI\n​Thông tin chi tiết có tại: https://thaylongtoeic.com/ho-tro-thi/\nNhấn vào hashtag để xem thêm các bài viết review và bảng điểm của các bạn đã từng học tại lớp em nhé\n👉 #thaylongreview #thaylongbangdiem\n————————————\n👉 CÁCH THỨC ĐĂNG KÝ\nEm đăng ký học trực tiếp trên website: https://thaylongtoeic.com/dangky/\nNếu cần thêm thông tin về khóa học, em inbox thầy cô sẽ giải đáp nhé 🫶\n————————————\n👉 ĐỊA CHỈ HỌC:\nCơ sở Hồ Tùng Mậu & Lê Đức Thọ: Số nhà 17B Ngõ 20 Hồ Tùng Mậu, Cầu Giấy, Hà Nội\nSố 9 Ngách 59 Ngõ 21 Lê Đức Thọ, Nam Từ Liêm, Hà Nội\nCơ sở Trần Đại Nghĩa: Tầng 4, 66 Trần Đại Nghĩa, Hai Bà Trưng, Hà Nội\nCơ Sở Hà Đông: Tầng 3 số 197 Trần Phú Hà Đông\nHotline + Zalo:\n0963352990 (Ms. Mỹ Linh)\n0961763990 (Ms. Thảo Đinh)",
    "cta_text": "Gửi tin nhắn",
    "start_date_readable": "14:00:00 10/07/2025",
    "end_date_readable": "14:00:00 15/07/2025",
    "duration_days": 5
  },
  {
    "is_active": true,
    "ad_archive_id": "597787383034352",
    "collation_id": "2226531191134383",
    "collation_count": 0,
    "page_id": "425181617530046",
    "page_name": "Lớp Toeic Thầy Long",
    "page_profile_uri": "https://www.facebook.com/ToeicThayLong/",
    "page_profile_picture_url": "https://scontent.fhan14-5.fna.fbcdn.net/v/t39.35426-6/517342162_2493338797689857_7468411308318251270_n.jpg?stp=dst-jpg_s60x60_tt6&_nc_cat=109&ccb=1-7&_nc_sid=c53f8f&_nc_ohc=39VlLKus9-QQ7kNvwEcPAJl&_nc_oc=AdnoFCxuGvmOZVm5PdNPWkdTp3sdCaQUdS6gn-WIVsEaSmQA3kVHDmXFSUBorhgZas4&_nc_zt=14&_nc_ht=scontent.fhan14-5.fna&_nc_gid=aHbkyQBIBM_3jnFGNUwwVQ&oh=00_AfTlP9c8j9ciUthQe7o0f1RTO_LkLdpbG1RG2Y2v1ZIm3w&oe=687C6EB4",
    "publisher_platform": [
      "FACEBOOK",
      "INSTAGRAM",
      "MESSENGER"
    ],
    "display_format": "IMAGE",
    "original_image_urls": [
      "https://scontent.fhan14-3.fna.fbcdn.net/v/t39.35426-6/517397255_582803361347527_9033670862318678314_n.jpg?_nc_cat=103&ccb=1-7&_nc_sid=c53f8f&_nc_ohc=TQ-4VZLgPdcQ7kNvwEDpobe&_nc_oc=Adm_l2JsI0tPXslMuX4UB7w8st_5McIeWQvsOdj0EB7r6fIUZE20-YaN4WURmrEq1MA&_nc_zt=14&_nc_ht=scontent.fhan14-3.fna&_nc_gid=aHbkyQBIBM_3jnFGNUwwVQ&oh=00_AfQE23Hs_6aklArB8xTHNt6Cn6Fsn1659Xg0dSvtm8fnew&oe=687C7FF6"
    ],
    "video_preview_image_url": null,
    "video_sd_url": null,
    "body_text": "📆 LỊCH KHAI GIẢNG MỚI NHẤT THÁNG 8-2025\n👉 Đừng bỏ lỡ những lịch học TOEIC 4 kỹ năng mới nhất tháng 8-2025 tại Lớp TOEIC Thầy Long\nXem lịch khai giảng gần nhất tại:\nhttps://thaylongtoeic.com/lich-khai-giang/\n————————————\n👉 THÔNG TIN LỚP HỌC:\n✅ Lớp Tập Sự: Dành cho các bạn mất gốc hoặc mới bắt đầu tiếng Anh\n⚬ Học phí gốc 3.200.000đ/22b + 6b bổ trợ âm Online\n⚬ Phát triển kỹ năng nghe cơ bản.\n⚬ Tích lũy từ vựng tiếng Anh đa chủ đề.\n⚬ Xây dựng khung ngữ pháp cơ bản.\n🎁 Ưu đãi của riêng lớp học\n⚬ Miễn phí tài liệu ôn tập và có website luyện đề giống thi thật tới 90%.\n⚬ Ưu đãi cho đăng ký và hoàn thành học phí sớm giảm còn 3.000.000đ.( áp dụng cho đăng ký và hoàn thành học phí trước khai giảng)\n✅ Lớp TOEIC A: KHOÁ LUYỆN THI DÀNH CHO CÁC BẠN ĐÃ CÓ NỀN TẢNG\n⚬ Học phí gốc 3.900.000 (27 buổi học trực tiếp trên lớp~ 2 tháng 1 tuần).\n⚬ Học phí gốc lớp Online được hưởng ưu đãi giảm 200.000đ chỉ còn 3.700.000đ.\n⚬ Đăng ký và hoàn thành học phí trước khai giảng được giảm còn 3.500.000đ với lớp trực tiếp và 3.300.000đ với lớp Online.\n⚬ Hoàn thành toàn bộ phần nghe trong bài thi TOEIC (Part 1-2-3-4).\n⚬ Hệ thống lại ngữ pháp chủ điểm.\n⚬ Làm quen với phần Reading trong bài thi Toeic.\n⚬ Sỹ số lớp học chỉ từ 23-25 học viên, giáo viên có thể sát sao như trải nghiệm học 1-1\n🎁 Ưu đãi của riêng lớp học\n⚬ Được cung cấp tài liệu miễn phí trong toàn bộ khoá học.\n⚬ Website luyện đề giống thi thật tới 90%, hơn 50 đề thi sát nhất với đề thi thật.\n⚬ Lớp Online được nhận file mềm giáo trình và được thầy cô hỗ trợ trong suốt khóa học.\n✅ Lớp TOEIC Speaking & Writing​​: Dành cho các bạn sau khi hoàn thành kỳ thi TOEIC Listening & Reading muốn nâng cao khả năng nói và viết trong môi trường làm việc quốc tế. Ngoài ra một số trường yêu cầu TOEIC 4 kỹ năng thì các em có thể tham gia nốt khóa học này để hoàn thiện và lấy chứng chỉ TOEIC SW.\n————————————\n🎁 ƯU ĐÃI KHÁC VÀ HỖ TRỢ THI\n​Thông tin chi tiết có tại: https://thaylongtoeic.com/ho-tro-thi/\nNhấn vào hashtag để xem thêm các bài viết review và bảng điểm của các bạn đã từng học tại lớp em nhé\n👉 #thaylongreview #thaylongbangdiem\n————————————\n👉 CÁCH THỨC ĐĂNG KÝ\nEm đăng ký học trực tiếp trên website: https://thaylongtoeic.com/dangky/\nNếu cần thêm thông tin về khóa học, em inbox thầy cô sẽ giải đáp nhé 🫶\n————————————\n👉 ĐỊA CHỈ HỌC:\nCơ sở Hồ Tùng Mậu & Lê Đức Thọ: Số nhà 17B Ngõ 20 Hồ Tùng Mậu, Cầu Giấy, Hà Nội\nSố 9 Ngách 59 Ngõ 21 Lê Đức Thọ, Nam Từ Liêm, Hà Nội\nCơ sở Trần Đại Nghĩa: Tầng 4, 66 Trần Đại Nghĩa, Hai Bà Trưng, Hà Nội\nCơ Sở Hà Đông: Tầng 3 số 197 Trần Phú Hà Đông\nHotline + Zalo:\n0963352990 (Ms. Mỹ Linh)\n0961763990 (Ms. Thảo Đinh)",
    "cta_text": "Gửi tin nhắn",
    "start_date_readable": "14:00:00 10/07/2025",
    "end_date_readable": "14:00:00 15/07/2025",
    "duration_days": 5
  },
  {
    "is_active": true,
    "ad_archive_id": "1495181344802064",
    "collation_id": "1074801491269431",
    "collation_count": 1,
    "page_id": "425181617530046",
    "page_name": "Lớp Toeic Thầy Long",
    "page_profile_uri": "https://www.facebook.com/ToeicThayLong/",
    "page_profile_picture_url": "https://scontent.fhan14-1.fna.fbcdn.net/v/t39.35426-6/518723934_1014999107380493_4141745469490948822_n.jpg?stp=dst-jpg_s60x60_tt6&_nc_cat=101&ccb=1-7&_nc_sid=c53f8f&_nc_ohc=4QJ0Q7g2ZhIQ7kNvwESYxUk&_nc_oc=AdnIp4eRfRykGC-p1hK62ZhWhF_ElD7EDdo2hALZzI2c7sw_Szsz7xykBRnUHcBngkA&_nc_zt=14&_nc_ht=scontent.fhan14-1.fna&_nc_gid=aHbkyQBIBM_3jnFGNUwwVQ&oh=00_AfSgmTghrJZK4ptg7cchyg4ASHzxbWfs4sDaS9BAlFhnMQ&oe=687C53D1",
    "publisher_platform": [
      "FACEBOOK",
      "INSTAGRAM",
      "AUDIENCE_NETWORK"
    ],
    "display_format": "VIDEO",
    "original_image_urls": [],
    "video_preview_image_url": null,
    "video_sd_url": null,
    "body_text": "Cùng theo dõi hành trình học tập của Minh Ngọc tại trung tâm nhé\nĐể tìm hiểu thêm về thông tin khoá học inbox trực tiếp cho thầy cô nhé❤️",
    "cta_text": "Gửi tin nhắn",
    "start_date_readable": "14:00:00 10/07/2025",
    "end_date_readable": "14:00:00 15/07/2025",
    "duration_days": 5
  },
  {
    "is_active": true,
    "ad_archive_id": "710297251797219",
    "collation_id": "1231394681332529",
    "collation_count": 1,
    "page_id": "425181617530046",
    "page_name": "Lớp Toeic Thầy Long",
    "page_profile_uri": "https://www.facebook.com/ToeicThayLong/",
    "page_profile_picture_url": "https://scontent.fhan14-1.fna.fbcdn.net/v/t39.35426-6/453397368_816351353962720_7315969681654972225_n.jpg?stp=dst-jpg_s60x60_tt6&_nc_cat=105&ccb=1-7&_nc_sid=c53f8f&_nc_ohc=i1RQ2AguWf4Q7kNvwGHuijM&_nc_oc=AdkPk7Kt2G2yeONs0lHIojkUY4LE3a-MAt7-8L3cHB9XG7X_BPR5u_59lZMGbG3QRXk&_nc_zt=14&_nc_ht=scontent.fhan14-1.fna&_nc_gid=aHbkyQBIBM_3jnFGNUwwVQ&oh=00_AfTavZR4Oc1vL0DXQDtOPteLGLy8rQ9U02lDbHOU-HRqlw&oe=687C72F4",
    "publisher_platform": [
      "FACEBOOK",
      "INSTAGRAM",
      "MESSENGER"
    ],
    "display_format": "VIDEO",
    "original_image_urls": [],
    "video_preview_image_url": null,
    "video_sd_url": null,
    "body_text": "HỌC NGÂN HÀNG CÓ CẦN GIỎI TIẾNG ANH KHÔNG?\n\nCùng nghe Quỳnh Anh chia sẻ về quá trình đạt được số điểm 885/990 TOEIC L&R sau khóa TOEIC A tại Lớp TOEIC thầy Long nhé\n-------\nInbox ngay để nhận thông tin về lớp TOEIC A tại Lớp 🫶\n#thaylongtoeic #thaylongbangdiem #thaylongreview",
    "cta_text": "Gửi tin nhắn",
    "start_date_readable": "14:00:00 08/07/2025",
    "end_date_readable": "14:00:00 14/07/2025",
    "duration_days": 6
  },
  {
    "is_active": true,
    "ad_archive_id": "740945568388888",
    "collation_id": "798028275763794",
    "collation_count": 1,
    "page_id": "425181617530046",
    "page_name": "Lớp Toeic Thầy Long",
    "page_profile_uri": "https://www.facebook.com/ToeicThayLong/",
    "page_profile_picture_url": "https://scontent.fhan14-5.fna.fbcdn.net/v/t39.35426-6/447888633_1160363671945317_2193185936117400185_n.jpg?stp=dst-jpg_s60x60_tt6&_nc_cat=104&ccb=1-7&_nc_sid=c53f8f&_nc_ohc=AwtDkYojMYoQ7kNvwEdd7Mj&_nc_oc=AdnOUOC9HYdkZmqMPXnSb_k8Vsw5y3vRA454KvyF-P7ZE6vcEsIz5dLkPielnvKRTdI&_nc_zt=14&_nc_ht=scontent.fhan14-5.fna&_nc_gid=aHbkyQBIBM_3jnFGNUwwVQ&oh=00_AfQUqj9eJfpiB2IvPGz8rxoqeu07usoDKy0tKrmMoxR4sg&oe=687C79BC",
    "publisher_platform": [
      "FACEBOOK",
      "INSTAGRAM",
      "MESSENGER"
    ],
    "display_format": "VIDEO",
    "original_image_urls": [],
    "video_preview_image_url": null,
    "video_sd_url": null,
    "body_text": "ĐÔI BẠN CÙNG TIẾN CÙNG ĐẠT 800+ TOEIC \nChúc mừng Trang và Tâm sinh viên năm cuối Học Viện Ngân Hàng với kết quả rất tốt sau lớp TOEIC A: 840, 865. Số điểm này giúp 2 em có thể để đổi điểm ra trường và đi xin việc. \nThầy cô chúc 2 em sẽ còn gặt hái thêm nhiều thành công hơn nữa nhé🫶\n---------------\nThông tin về khóa học, các em inbox thầy cô sẽ giải đáp nhé 🫶\n#thaylongtoeic #thaylongbangdiem #thaylongreview",
    "cta_text": "Gửi tin nhắn",
    "start_date_readable": "14:00:00 08/07/2025",
    "end_date_readable": "14:00:00 14/07/2025",
    "duration_days": 6
  },
  {
    "is_active": true,
    "ad_archive_id": "670670709260566",
    "collation_id": "646743161713061",
    "collation_count": 2,
    "page_id": "425181617530046",
    "page_name": "Lớp Toeic Thầy Long",
    "page_profile_uri": "https://www.facebook.com/ToeicThayLong/",
    "page_profile_picture_url": "https://scontent.fhan14-1.fna.fbcdn.net/v/t39.35426-6/514279908_2551673765177629_2435356247163169559_n.jpg?stp=dst-jpg_s60x60_tt6&_nc_cat=105&ccb=1-7&_nc_sid=c53f8f&_nc_ohc=Yo4SJHTYn1wQ7kNvwFBawMT&_nc_oc=Adn9IjRhA9UlwiXLxdNAPeKR6O8k2I9-n5ygT-jNwL7vt2NGlAbI4bwvtOB62PIQ7I0&_nc_zt=14&_nc_ht=scontent.fhan14-1.fna&_nc_gid=aHbkyQBIBM_3jnFGNUwwVQ&oh=00_AfRnghO1VZYnWiIXwTQ8yA1UF7oHu5qZXZlyI0v1HHAGEQ&oe=687C52B5",
    "publisher_platform": [
      "FACEBOOK",
      "MESSENGER"
    ],
    "display_format": "VIDEO",
    "original_image_urls": [],
    "video_preview_image_url": null,
    "video_sd_url": null,
    "body_text": "Cùng theo dõi hành trình học tập của Phương Anh cô sinh viên PTIT ( Học Viện Công Nghệ Bưu Chính Viễn Thông) và đạt 945/990 sau khoá học TOEIC A online nhé❤️",
    "cta_text": "Gửi tin nhắn",
    "start_date_readable": "14:00:00 29/06/2025",
    "end_date_readable": "14:00:00 14/07/2025",
    "duration_days": 15
  },
  {
    "is_active": true,
    "ad_archive_id": "725227726580518",
    "collation_id": "646743161713061",
    "collation_count": 0,
    "page_id": "425181617530046",
    "page_name": "Lớp Toeic Thầy Long",
    "page_profile_uri": "https://www.facebook.com/ToeicThayLong/",
    "page_profile_picture_url": "https://scontent.fhan14-4.fna.fbcdn.net/v/t39.35426-6/513716228_23964433483168175_7318789961537590052_n.jpg?stp=dst-jpg_s60x60_tt6&_nc_cat=102&ccb=1-7&_nc_sid=c53f8f&_nc_ohc=O7zh_C0jCucQ7kNvwFQm6rK&_nc_oc=AdlWZzGVPkziSMcSVXRw-lMz0gcThQcMpLAEzehmbvH0xLz8UJOTVeCxdrDzbwhfU74&_nc_zt=14&_nc_ht=scontent.fhan14-4.fna&_nc_gid=aHbkyQBIBM_3jnFGNUwwVQ&oh=00_AfRR9GvlEE7RUf6_E9Em7eB5bfkVstV2GkZ-ZmGK4mG93w&oe=687C88EA",
    "publisher_platform": [
      "FACEBOOK",
      "INSTAGRAM",
      "AUDIENCE_NETWORK"
    ],
    "display_format": "VIDEO",
    "original_image_urls": [],
    "video_preview_image_url": null,
    "video_sd_url": null,
    "body_text": "Cùng theo dõi hành trình học tập của Phương Anh cô sinh viên PTIT ( Học Viện Công Nghệ Bưu Chính Viễn Thông) và đạt 945/990 sau khoá học TOEIC A online nhé❤️",
    "cta_text": "Gửi tin nhắn",
    "start_date_readable": "14:00:00 28/06/2025",
    "end_date_readable": "14:00:00 15/07/2025",
    "duration_days": 17
  },
  {
    "is_active": true,
    "ad_archive_id": "1989043944836974",
    "collation_id": "1222426965797137",
    "collation_count": 1,
    "page_id": "425181617530046",
    "page_name": "Lớp Toeic Thầy Long",
    "page_profile_uri": "https://www.facebook.com/ToeicThayLong/",
    "page_profile_picture_url": "https://scontent.fhan14-3.fna.fbcdn.net/v/t39.35426-6/509630343_1478277799844015_2469352800834238442_n.jpg?stp=dst-jpg_s60x60_tt6&_nc_cat=103&ccb=1-7&_nc_sid=c53f8f&_nc_ohc=y6ZRv74l6dQQ7kNvwHDy5Ai&_nc_oc=AdlCctvhdGgjHvIFtA_AlT3PrdYpuRMPmqtBdsvXKMalFrpsjuW1pnGa6LcLqQvM6_o&_nc_zt=14&_nc_ht=scontent.fhan14-3.fna&_nc_gid=aHbkyQBIBM_3jnFGNUwwVQ&oh=00_AfTx56_9gkuUbPiPSca2oEwJYTqDmhBGG8isCygQHpyDrg&oe=687C8098",
    "publisher_platform": [
      "FACEBOOK",
      "INSTAGRAM",
      "MESSENGER",
      "THREADS"
    ],
    "display_format": "DCO",
    "original_image_urls": [],
    "video_preview_image_url": null,
    "video_sd_url": null,
    "body_text": "{{product.brand}}",
    "cta_text": "Tìm hiểu thêm",
    "start_date_readable": "14:00:00 27/06/2025",
    "end_date_readable": "14:00:00 14/07/2025",
    "duration_days": 17
  },
  {
    "is_active": true,
    "ad_archive_id": "686903017565243",
    "collation_id": "1705514593657917",
    "collation_count": 2,
    "page_id": "425181617530046",
    "page_name": "Lớp Toeic Thầy Long",
    "page_profile_uri": "https://www.facebook.com/ToeicThayLong/",
    "page_profile_picture_url": "https://scontent.fhan14-5.fna.fbcdn.net/v/t39.35426-6/464944499_545338878437530_4385002322775730151_n.jpg?stp=dst-jpg_s60x60_tt6&_nc_cat=109&ccb=1-7&_nc_sid=c53f8f&_nc_ohc=9jxW0f4V8kcQ7kNvwG4JXdg&_nc_oc=AdmHztH_nTTuDZXF7-v4fJd9i5DbqDBeLmVSPsk2BZd0cpe7OKm_Rb9UPI0w4bkDWu4&_nc_zt=14&_nc_ht=scontent.fhan14-5.fna&_nc_gid=aHbkyQBIBM_3jnFGNUwwVQ&oh=00_AfSqu1v9c35xH-LncVdp4nMsJAdbe1C4cmVGFcs66Cs7JA&oe=687C7370",
    "publisher_platform": [
      "FACEBOOK",
      "INSTAGRAM",
      "MESSENGER"
    ],
    "display_format": "DCO",
    "original_image_urls": [],
    "video_preview_image_url": null,
    "video_sd_url": null,
    "body_text": "{{product.brand}}",
    "cta_text": "Gửi tin nhắn",
    "start_date_readable": "14:00:00 12/06/2025",
    "end_date_readable": "14:00:00 14/07/2025",
    "duration_days": 32
  },
  {
    "is_active": true,
    "ad_archive_id": "652772854430860",
    "collation_id": "681026264741812",
    "collation_count": 2,
    "page_id": "425181617530046",
    "page_name": "Lớp Toeic Thầy Long",
    "page_profile_uri": "https://www.facebook.com/ToeicThayLong/",
    "page_profile_picture_url": "https://scontent.fhan14-2.fna.fbcdn.net/v/t39.35426-6/481956008_1779280336187787_5130176575888677195_n.jpg?stp=dst-jpg_s60x60_tt6&_nc_cat=100&ccb=1-7&_nc_sid=c53f8f&_nc_ohc=JhwDAGeO-o8Q7kNvwEQI0lR&_nc_oc=AdnJYICKlROZlVQu9tP6b4BRbHWSjVLF_ZJ0nqataEMS5BDMNmHl6fv99pz6gVqkWlg&_nc_zt=14&_nc_ht=scontent.fhan14-2.fna&_nc_gid=aHbkyQBIBM_3jnFGNUwwVQ&oh=00_AfRmVe6OV5wtIy_voE1D2tYvda1VKipMOiJxoGcuKox16Q&oe=687C6813",
    "publisher_platform": [
      "FACEBOOK",
      "INSTAGRAM",
      "MESSENGER"
    ],
    "display_format": "DCO",
    "original_image_urls": [],
    "video_preview_image_url": null,
    "video_sd_url": null,
    "body_text": "{{product.brand}}",
    "cta_text": "Gửi tin nhắn",
    "start_date_readable": "14:00:00 12/06/2025",
    "end_date_readable": "14:00:00 14/07/2025",
    "duration_days": 32
  },
  {
    "is_active": true,
    "ad_archive_id": "696128183384144",
    "collation_id": "1214346176888280",
    "collation_count": 2,
    "page_id": "425181617530046",
    "page_name": "Lớp Toeic Thầy Long",
    "page_profile_uri": "https://www.facebook.com/ToeicThayLong/",
    "page_profile_picture_url": "https://scontent.fhan14-3.fna.fbcdn.net/v/t39.35426-6/498199205_1075749284608143_6782305084155504272_n.jpg?stp=dst-jpg_s60x60_tt6&_nc_cat=111&ccb=1-7&_nc_sid=c53f8f&_nc_ohc=k4JMsEkZs9sQ7kNvwHCrWYL&_nc_oc=AdniUb_cfzdzA8PJKSsY1RiAA3NnCHzpf9y6JzynBpHj-Mac3zxGGh6_Y6-l0cL6898&_nc_zt=14&_nc_ht=scontent.fhan14-3.fna&_nc_gid=aHbkyQBIBM_3jnFGNUwwVQ&oh=00_AfQ70FhsvB0dx6seAdmS0giDyWc86QZ8j5BofqPaxGCOVQ&oe=687C5A3C",
    "publisher_platform": [
      "FACEBOOK",
      "INSTAGRAM",
      "MESSENGER"
    ],
    "display_format": "IMAGE",
    "original_image_urls": [
      "https://scontent.fhan14-3.fna.fbcdn.net/v/t39.35426-6/498118419_1242279154169145_4151313826935358170_n.jpg?_nc_cat=110&ccb=1-7&_nc_sid=c53f8f&_nc_ohc=4RWAPg2hMzkQ7kNvwEubErq&_nc_oc=AdmVQuueLJPnKd9I19kBmodPQ2MOq88pJPlnEFyQ7eM1cv6L1yuXoJZSkXwASskR6yU&_nc_zt=14&_nc_ht=scontent.fhan14-3.fna&_nc_gid=aHbkyQBIBM_3jnFGNUwwVQ&oh=00_AfRJrE-ePUN1A1ki735qNXlQ5a30TthWp8aEU5CnBqzWQg&oe=687C57DA"
    ],
    "video_preview_image_url": null,
    "video_sd_url": null,
    "body_text": "📣 Bạn đã có nền tảng tiếng Anh nhưng vẫn “đuối” khi luyện thi TOEIC?\nHãy để đội ngũ giảng viên 980+ TOEIC tại Lớp TOEIC Thầy Long giúp bạn chinh phục mục tiêu.\n\n🔥 Lớp TOEIC A – khóa học luyện đề, ôn tập trọng tâm, củng cố toàn diện kỹ năng Part 1-2-3-4 + Reading.\n🎯 Sỹ số nhỏ 23-25 HV – Giáo viên sát sao, sửa bài kỹ như học 1-1.\n➡️ Lịch khai giảng & ưu đãi: https://thaylongtoeic.com/lich-khai-giang/",
    "cta_text": "Gửi tin nhắn",
    "start_date_readable": "14:00:00 12/06/2025",
    "end_date_readable": "14:00:00 14/07/2025",
    "duration_days": 32
  },
  {
    "is_active": true,
    "ad_archive_id": "697918116433729",
    "collation_id": "1504693347629322",
    "collation_count": 2,
    "page_id": "425181617530046",
    "page_name": "Lớp Toeic Thầy Long",
    "page_profile_uri": "https://www.facebook.com/ToeicThayLong/",
    "page_profile_picture_url": "https://scontent.fhan14-3.fna.fbcdn.net/v/t39.35426-6/499606357_661906809995021_1132646144083314724_n.jpg?stp=dst-jpg_s60x60_tt6&_nc_cat=110&ccb=1-7&_nc_sid=c53f8f&_nc_ohc=Du0eNzN7GmwQ7kNvwFkPN8C&_nc_oc=AdkbL5jprhneo1csDuw-vCMg-e5R0cc2G1_gwI6qY70szH_VuKa6agqdivh7a43t-7s&_nc_zt=14&_nc_ht=scontent.fhan14-3.fna&_nc_gid=aHbkyQBIBM_3jnFGNUwwVQ&oh=00_AfSr3U5KCZwCCHUWZUDsckiyDPmQJ9_xLVM65xLBnFG3sQ&oe=687C66E3",
    "publisher_platform": [
      "FACEBOOK",
      "INSTAGRAM",
      "MESSENGER"
    ],
    "display_format": "DCO",
    "original_image_urls": [],
    "video_preview_image_url": null,
    "video_sd_url": null,
    "body_text": "{{product.brand}}",
    "cta_text": "Gửi tin nhắn",
    "start_date_readable": "14:00:00 12/06/2025",
    "end_date_readable": "14:00:00 14/07/2025",
    "duration_days": 32
  },
  {
    "is_active": true,
    "ad_archive_id": "1409438550209878",
    "collation_id": "1446787079641785",
    "collation_count": 1,
    "page_id": "425181617530046",
    "page_name": "Lớp Toeic Thầy Long",
    "page_profile_uri": "https://www.facebook.com/ToeicThayLong/",
    "page_profile_picture_url": "https://scontent.fhan14-5.fna.fbcdn.net/v/t39.35426-6/492399838_652931794296669_2538537171133361636_n.jpg?stp=dst-jpg_s60x60_tt6&_nc_cat=109&ccb=1-7&_nc_sid=c53f8f&_nc_ohc=4BxItpb8frEQ7kNvwHsVmZ0&_nc_oc=AdkWIoxod1SdMjlN8DCJDmv0dN-O9RRG_tOcep4oeZhUMdceuWsSnfUKlbDofJ1a1NI&_nc_zt=14&_nc_ht=scontent.fhan14-5.fna&_nc_gid=aHbkyQBIBM_3jnFGNUwwVQ&oh=00_AfQy1YUgo3o8JdhqQoknL3lECukXiaZUZWiBukFAmskq3g&oe=687C843E",
    "publisher_platform": [
      "FACEBOOK",
      "INSTAGRAM",
      "MESSENGER"
    ],
    "display_format": "VIDEO",
    "original_image_urls": [],
    "video_preview_image_url": null,
    "video_sd_url": null,
    "body_text": "Lộ trình 02 khoá học từ mất gốc đạt 550+\nCam kết đầu ra mục tiêu 550+ sau 5 tháng\n————————————\n👉 LỘ TRÌNH 02 khoá học bao gồm:\n✅ Giai đoạn 01: Dành cho các bạn mất gốc tiếng Anh\nLỚP TẬP SỰ:\n⚬ 3.200.000đ (22 buổi + 6 buổi bổ trợ âm)\n⚬ Phát triển kỹ năng nghe cơ bản\n⚬ Tích lũy từ vựng\n⚬ Học ngữ pháp cơ bản\nƯu đãi lớp học\n⚬ Miễn phí tài liệu\n⚬ Đăng ký và hoàn thành học phí trước khai giảng giảm còn 3.000.000đ\n✅ Giai đoạn 02: Nếu các bạn có sẵn nền tảng có thể bắt đầu học từ giai đoạn 02\nLỚP TOEIC A:\n⚬ 27 buổi học (2 tháng 1 tuần)\n⚬ Hoàn thành toàn bộ phần nghe (part 1-2-3-4 )\n⚬ Hệ thống lại ngữ pháp cơ bản\n⚬ Làm quen với phần Reading cơ bản\n⚬ Sỹ số lớp học: 23-25 học viên\n⚬ Học phí gốc 3.900.000/27 buổi học (lớp học trực tiếp)\nƯu đãi lớp học\n⚬ Học phí đã bao gồm tài liệu toàn bộ khoá học.\n⚬ Đăng ký và hoàn thành học phí trước khai giảng giảm còn 3.500.000đ\n\n✅ COMBO LỘ TRÌNH 550+: 6.000.000đ tiết kiệm 1.100.000đ so với đăng ký lẻ\n\n————————————\n🎁 ƯU ĐÃI KHÁC VÀ HỖ TRỢ THI KHÁC \n​Thông tin chi tiết có tại: https://thaylongtoeic.com/ho-tro-thi/\nNhấn vào hashtag để xem thêm các bài viết review và bảng điểm của lớp bạn nhé 👉 #thaylongreview #thaylongbangdiem\n————————————\n👉 CÁCH THỨC ĐĂNG KÝ\nĐăng ký học trực tiếp trên website: https://thaylongtoeic.com/dangky/\nHoặc nhắn tin để nhận tư vấn thêm về thông tin khoá học và đăng ký\n————————————\n👉 ĐỊA CHỈ HỌC:\nCơ sở Hồ Tùng Mậu & Lê Đức Thọ: Số nhà 17B Ngõ 20 Hồ Tùng Mậu, Cầu Giấy, Hà Nội\nSố 9 Ngách 59 Ngõ 21 Lê Đức Thọ, Nam Từ Liêm, Hà Nội\nCơ sở Trần Đại Nghĩa: Tầng 4, 66 Trần Đại Nghĩa, Hai Bà Trưng, Hà Nội\nCơ Sở Hà Đông: Tầng 3 số 197 Trần Phú Hà Đông\nHotline + Zalo:\n0963352990 (Ms. Hà Linh)\n0961763990 (Ms. Thảo Đinh)",
    "cta_text": "Gửi tin nhắn",
    "start_date_readable": "14:00:00 12/06/2025",
    "end_date_readable": "14:00:00 14/07/2025",
    "duration_days": 32
  },
  {
    "is_active": true,
    "ad_archive_id": "2782185438651324",
    "collation_id": "669680772533913",
    "collation_count": 4,
    "page_id": "425181617530046",
    "page_name": "Lớp Toeic Thầy Long",
    "page_profile_uri": "https://www.facebook.com/ToeicThayLong/",
    "page_profile_picture_url": "https://scontent.fhan14-2.fna.fbcdn.net/v/t39.35426-6/501666810_1247871300018689_6150141555638010898_n.jpg?stp=dst-jpg_s60x60_tt6&_nc_cat=100&ccb=1-7&_nc_sid=c53f8f&_nc_ohc=-urBLHJxGzkQ7kNvwF4g2P4&_nc_oc=Adk268CVGsMYnE_MYwHTE6lVHwOcfiGl6I9LBhyiJCwc87f6EetLFQI9AlKSOkSZHtw&_nc_zt=14&_nc_ht=scontent.fhan14-2.fna&_nc_gid=aHbkyQBIBM_3jnFGNUwwVQ&oh=00_AfSIeXuJksYZlDfq2ChnKXhoGJaXYnz9OKPPpMShwv-x4g&oe=687C5556",
    "publisher_platform": [
      "FACEBOOK",
      "INSTAGRAM",
      "MESSENGER"
    ],
    "display_format": "IMAGE",
    "original_image_urls": [
      "https://scontent.fhan14-5.fna.fbcdn.net/v/t39.35426-6/502451692_1424327748586700_7544371901262649705_n.jpg?_nc_cat=104&ccb=1-7&_nc_sid=c53f8f&_nc_ohc=kQF2Z9qdQbAQ7kNvwGtxDqV&_nc_oc=Adlj8EycsZ_yuW0JGIt5JGc8d-poET8KnNrMjoWmssQ0TFv1ICGfxerjKzkxJlUnwYo&_nc_zt=14&_nc_ht=scontent.fhan14-5.fna&_nc_gid=aHbkyQBIBM_3jnFGNUwwVQ&oh=00_AfTgZ1V2teTIjS9wTmgdppdpqOZZvUT-VB6KOQ79_96gUg&oe=687C596B"
    ],
    "video_preview_image_url": null,
    "video_sd_url": null,
    "body_text": "📆 LỊCH KHAI GIẢNG MỚI NHẤT THÁNG 7-2025\n👉 Đừng bỏ lỡ những lịch học TOEIC 4 kỹ năng mới nhất tháng 7-2025 tại Lớp TOEIC Thầy Long\nXem lịch khai giảng gần nhất tại:\nhttps://thaylongtoeic.com/lich-khai-giang/\n————————————\n👉 THÔNG TIN LỚP HỌC:\n✅ Lớp Tập Sự: Dành cho các bạn mất gốc hoặc mới bắt đầu tiếng Anh\n⚬ Học phí gốc 3.200.000đ/22b + 6b bổ trợ âm Online\n⚬ Phát triển kỹ năng nghe cơ bản.\n⚬ Tích lũy từ vựng tiếng Anh đa chủ đề.\n⚬ Xây dựng khung ngữ pháp cơ bản.\n🎁 Ưu đãi của riêng lớp học\n⚬ Miễn phí tài liệu ôn tập và có website luyện đề giống thi thật tới 90%.\n⚬ Ưu đãi cho đăng ký và hoàn thành học phí sớm giảm còn 3.000.000đ.( áp dụng cho đăng ký và hoàn thành học phí trước khai giảng)\n✅ Lớp TOEIC A: KHOÁ LUYỆN THI DÀNH CHO CÁC BẠN ĐÃ CÓ NỀN TẢNG\n⚬ Học phí gốc 3.900.000 (27 buổi học trực tiếp trên lớp~ 2 tháng 1 tuần).\n⚬ Học phí gốc lớp Online được hưởng ưu đãi giảm 200.000đ chỉ còn 3.700.000đ.\n⚬ Đăng ký và hoàn thành học phí trước khai giảng được giảm còn 3.500.000đ với lớp trực tiếp và 3.300.000đ với lớp Online.\n⚬ Hoàn thành toàn bộ phần nghe trong bài thi TOEIC (Part 1-2-3-4).\n⚬ Hệ thống lại ngữ pháp chủ điểm.\n⚬ Làm quen với phần Reading trong bài thi Toeic.\n⚬ Sỹ số lớp học chỉ từ 23-25 học viên, giáo viên có thể sát sao như trải nghiệm học 1-1\n🎁 Ưu đãi của riêng lớp học\n⚬ Được cung cấp tài liệu miễn phí trong toàn bộ khoá học.\n⚬ Website luyện đề giống thi thật tới 90%, hơn 50 đề thi sát nhất với đề thi thật.\n⚬ Lớp Online được nhận file mềm giáo trình và được thầy cô hỗ trợ trong suốt khóa học.\n✅ Lớp TOEIC Speaking & Writing​​: Dành cho các bạn sau khi hoàn thành kỳ thi TOEIC Listening & Reading muốn nâng cao khả năng nói và viết trong môi trường làm việc quốc tế. Ngoài ra một số trường yêu cầu TOEIC 4 kỹ năng thì các em có thể tham gia nốt khóa học này để hoàn thiện và lấy chứng chỉ TOEIC SW.\n————————————\n🎁 ƯU ĐÃI KHÁC VÀ HỖ TRỢ THI\n​Thông tin chi tiết có tại: https://thaylongtoeic.com/ho-tro-thi/\nNhấn vào hashtag để xem thêm các bài viết review và bảng điểm của các bạn đã từng học tại lớp em nhé\n👉 #thaylongreview #thaylongbangdiem\n————————————\n👉 CÁCH THỨC ĐĂNG KÝ\nEm đăng ký học trực tiếp trên website: https://thaylongtoeic.com/dangky/\nNếu cần thêm thông tin về khóa học, em inbox thầy cô sẽ giải đáp nhé 🫶\n————————————\n👉 ĐỊA CHỈ HỌC:\nCơ sở Hồ Tùng Mậu & Lê Đức Thọ: Số nhà 17B Ngõ 20 Hồ Tùng Mậu, Cầu Giấy, Hà Nội\nSố 9 Ngách 59 Ngõ 21 Lê Đức Thọ, Nam Từ Liêm, Hà Nội\nCơ sở Trần Đại Nghĩa: Tầng 4, 66 Trần Đại Nghĩa, Hai Bà Trưng, Hà Nội\nCơ Sở Hà Đông: Tầng 3 số 197 Trần Phú Hà Đông\nHotline + Zalo:\n0963352990 (Ms. Mỹ Linh)\n0961763990 (Ms. Thảo Đinh)",
    "cta_text": "Gửi tin nhắn",
    "start_date_readable": "14:00:00 12/06/2025",
    "end_date_readable": "14:00:00 13/07/2025",
    "duration_days": 31
  },
  {
    "is_active": true,
    "ad_archive_id": "3541248736006580",
    "collation_id": "1390924658744496",
    "collation_count": 2,
    "page_id": "425181617530046",
    "page_name": "Lớp Toeic Thầy Long",
    "page_profile_uri": "https://www.facebook.com/ToeicThayLong/",
    "page_profile_picture_url": "https://scontent.fhan14-1.fna.fbcdn.net/v/t39.35426-6/492389552_1418845252822845_7920787271234290423_n.jpg?stp=dst-jpg_s60x60_tt6&_nc_cat=105&ccb=1-7&_nc_sid=c53f8f&_nc_ohc=jjG783ytHUcQ7kNvwGF8LmK&_nc_oc=AdnUn90x5ngtk8aSypN1eGNi_MYxxUtoShCG0WkUtIOUZ7rHJ2FdFZEtzT0Ju0MvZ5U&_nc_zt=14&_nc_ht=scontent.fhan14-1.fna&_nc_gid=aHbkyQBIBM_3jnFGNUwwVQ&oh=00_AfRBu7xm4MzRPrrBCVO9qFjOyRfJ1dpLc5QgJfJS-zV69g&oe=687C864E",
    "publisher_platform": [
      "FACEBOOK",
      "INSTAGRAM",
      "MESSENGER"
    ],
    "display_format": "IMAGE",
    "original_image_urls": [
      "https://scontent.fhan14-5.fna.fbcdn.net/v/t39.35426-6/492518498_1656292829095924_2826990291526220256_n.jpg?_nc_cat=109&ccb=1-7&_nc_sid=c53f8f&_nc_ohc=GTBzx8a4HGIQ7kNvwH5Qxij&_nc_oc=Admyt6hdgcGQ4EtXcIlAKTJaQy55U2T-jFR8crtpcRPBOrtwV5Fa17C0SQk4RdBxgP0&_nc_zt=14&_nc_ht=scontent.fhan14-5.fna&_nc_gid=aHbkyQBIBM_3jnFGNUwwVQ&oh=00_AfRU8AYvf3gX-a_v_KjbP1mUUZycLTWnKGTBOUlu-04snQ&oe=687C80A4"
    ],
    "video_preview_image_url": null,
    "video_sd_url": null,
    "body_text": "Chinh phục TOEIC dễ dàng với đội ngũ giảng viên chất lượng tại Lớp TOEIC thầy Long",
    "cta_text": "Gửi tin nhắn",
    "start_date_readable": "14:00:00 12/06/2025",
    "end_date_readable": "14:00:00 14/07/2025",
    "duration_days": 32
  },
  {
    "is_active": true,
    "ad_archive_id": "611137925345915",
    "collation_id": "1407409947349558",
    "collation_count": 2,
    "page_id": "425181617530046",
    "page_name": "Lớp Toeic Thầy Long",
    "page_profile_uri": "https://www.facebook.com/ToeicThayLong/",
    "page_profile_picture_url": "https://scontent.fhan14-2.fna.fbcdn.net/v/t39.35426-6/497529612_704652635369454_1554278613532118708_n.jpg?stp=dst-jpg_s60x60_tt6&_nc_cat=108&ccb=1-7&_nc_sid=c53f8f&_nc_ohc=fxC3RgNzu6gQ7kNvwGTHCy0&_nc_oc=AdkeHuC2ErwG7_BDVTMK9pOuFMOkMRHQ6ide1GpYCVK2g5wAfxEQdxIp71hjBvEC9Lg&_nc_zt=14&_nc_ht=scontent.fhan14-2.fna&_nc_gid=aHbkyQBIBM_3jnFGNUwwVQ&oh=00_AfQeAjseQznY2xlgjFEflC8FMap_rZDwBGqbnk8_SXC7LQ&oe=687C544E",
    "publisher_platform": [
      "FACEBOOK",
      "INSTAGRAM",
      "MESSENGER"
    ],
    "display_format": "IMAGE",
    "original_image_urls": [
      "https://scontent.fhan14-5.fna.fbcdn.net/v/t39.35426-6/498185390_2456585394695100_1832574387436353532_n.jpg?_nc_cat=109&ccb=1-7&_nc_sid=c53f8f&_nc_ohc=JPzxVdK2qbQQ7kNvwEFNd6T&_nc_oc=Adl1zdJi-nY1W4jUuSIU4vXxDUrknoPMd4WKcVmL-K44zFAl9CikRQEVTVcSUKs9YVE&_nc_zt=14&_nc_ht=scontent.fhan14-5.fna&_nc_gid=aHbkyQBIBM_3jnFGNUwwVQ&oh=00_AfSxOB4T87-l4xrNcYQy6f_U8CxrGGCTz5q-83cO1hkzQA&oe=687C6474"
    ],
    "video_preview_image_url": null,
    "video_sd_url": null,
    "body_text": "Lộ trình 02 khoá học từ mất gốc đạt 550+ TOEIC\nCam kết đầu ra mục tiêu 550+ sau 5 tháng\n————————————\n👉 LỘ TRÌNH 02 khoá học bao gồm:\n✅ Giai đoạn 01: Dành cho các bạn mất gốc tiếng Anh\nLỚP TẬP SỰ:\n⚬ 3.200.000đ (28 buổi) (2,5 tháng)\n⚬ Phát triển kỹ năng nghe cơ bản\n⚬ Tích lũy từ vựng\n⚬ Học ngữ pháp cơ bản\nƯu đãi lớp học\n⚬ Miễn phí tài liệu\n⚬ Đăng ký và hoàn thành học phí trước khai giảng giảm còn 3.000.000đ\n✅ Giai đoạn 02: Nếu các bạn có sẵn nền tảng có thể bắt đầu học từ giai đoạn 02\nLỚP TOEIC A:\n⚬ 27 buổi học (2 tháng 1 tuần)\n⚬ Hoàn thành toàn bộ phần nghe (part 1-2-3-4 )\n⚬ Hệ thống lại ngữ pháp cơ bản\n⚬ Làm quen với phần Reading cơ bản\n⚬ Sỹ số lớp học: 23-25 học viên\n⚬ Học phí gốc 3.900.000/27 buổi học (lớp học trực tiếp)\nƯu đãi lớp học\n⚬ Học phí đã bao gồm tài liệu toàn bộ khoá học.\n⚬ Đăng ký và hoàn thành học phí trước khai giảng giảm còn 3.500.000đ\n✅ COMBO LỘ TRÌNH 550+: 6.000.000đ tiết kiệm 1.100.000đ so với đăng ký lẻ\n————————————\n🎁 ƯU ĐÃI KHÁC VÀ HỖ TRỢ THI KHÁC \n​Thông tin chi tiết có tại: https://thaylongtoeic.com/ho-tro-thi/\nNhấn vào hashtag để xem thêm các bài viết review và bảng điểm của lớp bạn nhé 👉 #thaylongreview #thaylongbangdiem\n————————————\n👉 CÁCH THỨC ĐĂNG KÝ\nNhắn tin để nhận tư vấn thêm về thông tin khoá học và đăng ký\n————————————\n👉 ĐỊA CHỈ HỌC:\nCơ sở Hồ Tùng Mậu : Số nhà 17B Ngõ 20 Hồ Tùng Mậu, Cầu Giấy, Hà Nội\nCơ sở Lê Đức Thọ: Số 9 Ngách 59 Ngõ 21 Lê Đức Thọ, Nam Từ Liêm, Hà Nội\nCơ Sở Hà Đông: Tầng 3 số 197 Trần Phú Hà Đông\nHotline + Zalo:\n0963352990 (Ms. Hà Linh)\n0961763990 (Ms. Thảo Đinh)",
    "cta_text": "Gửi tin nhắn",
    "start_date_readable": "14:00:00 12/06/2025",
    "end_date_readable": "14:00:00 14/07/2025",
    "duration_days": 32
  },
  {
    "is_active": true,
    "ad_archive_id": "675658555285446",
    "collation_id": "1480157109624111",
    "collation_count": 1,
    "page_id": "425181617530046",
    "page_name": "Lớp Toeic Thầy Long",
    "page_profile_uri": "https://www.facebook.com/ToeicThayLong/",
    "page_profile_picture_url": "https://scontent.fhan14-3.fna.fbcdn.net/v/t39.35426-6/492006838_1047747223882835_8571560386306770347_n.jpg?stp=dst-jpg_s60x60_tt6&_nc_cat=111&ccb=1-7&_nc_sid=c53f8f&_nc_ohc=-MKM5VdKzYYQ7kNvwF5R6dk&_nc_oc=AdmMQI6we4cjc6T-4k1PSb6M8GHQorn3UtA9w7IkBOx1uUrzP37QDsKE4459i5FWC6Y&_nc_zt=14&_nc_ht=scontent.fhan14-3.fna&_nc_gid=aHbkyQBIBM_3jnFGNUwwVQ&oh=00_AfRrSjsHoQ_yAi83z4j3masBGac_B5rXWyE7Himi8Zhi8A&oe=687C82FC",
    "publisher_platform": [
      "FACEBOOK",
      "INSTAGRAM",
      "MESSENGER"
    ],
    "display_format": "VIDEO",
    "original_image_urls": [],
    "video_preview_image_url": null,
    "video_sd_url": null,
    "body_text": "🫶 Đạt mục tiêu TOEIC 4 kỹ năng từ MẤT GỐC tại Lớp TOEIC thầy Long ngay hôm nay\n————————————\n👉 THÔNG TIN LỚP HỌC:\n✅ Lớp Tập Sự: Dành cho các bạn mất gốc hoặc mới bắt đầu tiếng Anh\n⚬ Học phí gốc 3.200.000\n⚬ Phát triển kỹ năng nghe cơ bản.\n⚬ Tích lũy từ vựng tiếng Anh đa chủ đề.\n⚬ Xây dựng khung ngữ pháp cơ bản.\n🎁 Ưu đãi của riêng lớp học\n⚬ Miễn phí tài liệu ôn tập và có website luyện đề giống thi thật tới 90%.\n⚬ Ưu đãi cho đăng ký và hoàn thành học phí sớm giảm còn 3.000.000đ.( áp dụng cho đăng ký và hoàn thành học phí trước khai giảng)\n✅ Lớp TOEIC A: KHOÁ LUYỆN THI DÀNH CHO CÁC BẠN ĐÃ CÓ NỀN TẢNG\n⚬ Học phí gốc 3.900.000 (27 buổi học trực tiếp trên lớp~ 2 tháng 1 tuần).\n⚬ Hoàn thành toàn bộ phần nghe trong bài thi TOEIC (Part 1-2-3-4).\n⚬ Hệ thống lại ngữ pháp chủ điểm.\n⚬ Làm quen với phần Reading trong bài thi Toeic.\n⚬ Sỹ số lớp học chỉ từ 23-25 học viên, giáo viên có thể sát sao như trải nghiệm học 1-1\n🎁 Ưu đãi của riêng lớp học\n⚬ Được cung cấp tài liệu miễn phí trong toàn bộ khoá học.\n⚬ Website luyện đề giống thi thật tới 90%, hơn 50 đề thi sát nhất với đề thi thật.\n⚬ Đăng ký và hoàn thành học phí trước khai giảng được giảm còn 3.500.000đ\n✅ Lớp TOEIC Speaking & Writing​​: Dành cho các bạn sau khi hoàn thành kỳ thi TOEIC Listening & Reading muốn nâng cao khả năng nói và viết trong môi trường làm việc quốc tế. Ngoài ra một số trường yêu cầu TOEIC 4 kỹ năng thì các em có thể tham gia nốt khóa học này để hoàn thiện và lấy chứng chỉ TOEIC SW.\n————————————\n👉 CÁCH THỨC ĐĂNG KÝ\nNhắn tin để nhận tư vấn thêm về thông tin khoá học và đăng ký\n————————————\n👉 ĐỊA CHỈ HỌC:\nCơ sở Hồ Tùng Mậu & Lê Đức Thọ: Số nhà 17B Ngõ 20 Hồ Tùng Mậu, Cầu Giấy, Hà Nội\nSố 9 Ngách 59 Ngõ 21 Lê Đức Thọ, Nam Từ Liêm, Hà Nội\nCơ sở Trần Đại Nghĩa: Tầng 4, 66 Trần Đại Nghĩa, Hai Bà Trưng, Hà Nội\nCơ Sở Hà Đông: Tầng 3 số 197 Trần Phú Hà Đông\nHotline + Zalo:\n0963352990 (Ms. Hà Linh)\n0961763990 (Ms. Thảo Đinh)",
    "cta_text": "Gửi tin nhắn",
    "start_date_readable": "14:00:00 12/06/2025",
    "end_date_readable": "14:00:00 14/07/2025",
    "duration_days": 32
  },
  {
    "is_active": true,
    "ad_archive_id": "1057260646368828",
    "collation_id": "619245807814340",
    "collation_count": 4,
    "page_id": "425181617530046",
    "page_name": "Lớp Toeic Thầy Long",
    "page_profile_uri": "https://www.facebook.com/ToeicThayLong/",
    "page_profile_picture_url": "https://scontent.fhan14-4.fna.fbcdn.net/v/t39.35426-6/497694539_563580756407071_5298807828154059638_n.jpg?stp=dst-jpg_s60x60_tt6&_nc_cat=107&ccb=1-7&_nc_sid=c53f8f&_nc_ohc=gbufZVrGsb4Q7kNvwGNS53Y&_nc_oc=AdndW9FLtH2Iaojo7-43n8AHYuGeCjK_BlxSrH1JqA-O7uGnPbdP1HG1vjlIX6XLa7Q&_nc_zt=14&_nc_ht=scontent.fhan14-4.fna&_nc_gid=aHbkyQBIBM_3jnFGNUwwVQ&oh=00_AfSGfH4zri6DDHYmTA58CbKFE2Oj6CrpLI9mQVyTz8CahQ&oe=687C6751",
    "publisher_platform": [
      "FACEBOOK",
      "INSTAGRAM",
      "MESSENGER"
    ],
    "display_format": "IMAGE",
    "original_image_urls": [
      "https://scontent.fhan14-1.fna.fbcdn.net/v/t39.35426-6/497510566_1205387571230537_7149793674572395983_n.jpg?_nc_cat=101&ccb=1-7&_nc_sid=c53f8f&_nc_ohc=F_qr5w7LpX8Q7kNvwF2XSwU&_nc_oc=AdlpM0m3Wm0LD-RF68KQsFnsH56M7pPKGIh0Dva4B2DyAJXXw0m1TLzk1aQEpf_A5_E&_nc_zt=14&_nc_ht=scontent.fhan14-1.fna&_nc_gid=aHbkyQBIBM_3jnFGNUwwVQ&oh=00_AfRQBhJCL6qmL0BtC7kvNDyI3Z-NqL86qLeFPr0_p4RXQQ&oe=687C80FF"
    ],
    "video_preview_image_url": null,
    "video_sd_url": null,
    "body_text": "📆 LỊCH KHAI GIẢNG MỚI NHẤT THÁNG 6 -2025\n👉 Đừng bỏ lỡ những lịch học TOEIC 4 kỹ năng mới nhất tháng 6-2025 tại Lớp TOEIC Thầy Long\nXem lịch khai giảng gần nhất tại:\nhttps://thaylongtoeic.com/lich-khai-giang/\n————————————\n👉 THÔNG TIN LỚP HỌC:\n✅ Lớp Tập Sự: Dành cho các bạn mất gốc hoặc mới bắt đầu tiếng Anh\n⚬ Học phí gốc 3.200.000đ/22b + 6b bổ trợ âm Online\n⚬ Phát triển kỹ năng nghe cơ bản.\n⚬ Tích lũy từ vựng tiếng Anh đa chủ đề.\n⚬ Xây dựng khung ngữ pháp cơ bản.\n🎁 Ưu đãi của riêng lớp học\n⚬ Miễn phí tài liệu ôn tập và có website luyện đề giống thi thật tới 90%.\n⚬ Ưu đãi cho đăng ký và hoàn thành học phí sớm giảm còn 3.000.000đ.( áp dụng cho đăng ký và hoàn thành học phí trước khai giảng)\n✅ Lớp TOEIC A: KHOÁ LUYỆN THI DÀNH CHO CÁC BẠN ĐÃ CÓ NỀN TẢNG\n⚬ Học phí gốc 3.900.000 (27 buổi học trực tiếp trên lớp~ 2 tháng 1 tuần).\n⚬ Học phí gốc lớp Online được hưởng ưu đãi giảm 200.000đ chỉ còn 3.700.000đ.\n⚬ Đăng ký và hoàn thành học phí trước khai giảng được giảm còn 3.500.000đ với lớp trực tiếp và 3.300.000đ với lớp Online.\n⚬ Hoàn thành toàn bộ phần nghe trong bài thi TOEIC (Part 1-2-3-4).\n⚬ Hệ thống lại ngữ pháp chủ điểm.\n⚬ Làm quen với phần Reading trong bài thi Toeic.\n⚬ Sỹ số lớp học chỉ từ 23-25 học viên, giáo viên có thể sát sao như trải nghiệm học 1-1\n🎁 Ưu đãi của riêng lớp học\n⚬ Được cung cấp tài liệu miễn phí trong toàn bộ khoá học.\n⚬ Website luyện đề giống thi thật tới 90%, hơn 50 đề thi sát nhất với đề thi thật.\n⚬ Lớp Online được nhận file mềm giáo trình và được thầy cô hỗ trợ trong suốt khóa học.\n✅ Lớp TOEIC Speaking & Writing​​: Dành cho các bạn sau khi hoàn thành kỳ thi TOEIC Listening & Reading muốn nâng cao khả năng nói và viết trong môi trường làm việc quốc tế. Ngoài ra một số trường yêu cầu TOEIC 4 kỹ năng thì các em có thể tham gia nốt khóa học này để hoàn thiện và lấy chứng chỉ TOEIC SW.\n————————————\n🎁 ƯU ĐÃI KHÁC VÀ HỖ TRỢ THI\n​Thông tin chi tiết có tại: https://thaylongtoeic.com/ho-tro-thi/\nNhấn vào hashtag để xem thêm các bài viết review và bảng điểm của các bạn đã từng học tại lớp em nhé\n👉 #thaylongreview #thaylongbangdiem\n————————————\n👉 CÁCH THỨC ĐĂNG KÝ\nEm đăng ký học trực tiếp trên website: https://thaylongtoeic.com/dangky/\nNếu cần thêm thông tin về khóa học, em inbox thầy cô sẽ giải đáp nhé 🫶\n————————————\n👉 ĐỊA CHỈ HỌC:\nCơ sở Hồ Tùng Mậu & Lê Đức Thọ: Số nhà 17B Ngõ 20 Hồ Tùng Mậu, Cầu Giấy, Hà Nội\nSố 9 Ngách 59 Ngõ 21 Lê Đức Thọ, Nam Từ Liêm, Hà Nội\nCơ sở Trần Đại Nghĩa: Tầng 4, 66 Trần Đại Nghĩa, Hai Bà Trưng, Hà Nội\nCơ Sở Hà Đông: Tầng 3 số 197 Trần Phú Hà Đông\nHotline + Zalo:\n0963352990 (Ms. Mỹ Linh)\n0961763990 (Ms. Thảo Đinh)",
    "cta_text": "Gửi tin nhắn",
    "start_date_readable": "14:00:00 12/06/2025",
    "end_date_readable": "14:00:00 14/07/2025",
    "duration_days": 32
  },
  {
    "is_active": true,
    "ad_archive_id": "1412360483102863",
    "collation_id": "1567952057445188",
    "collation_count": 2,
    "page_id": "425181617530046",
    "page_name": "Lớp Toeic Thầy Long",
    "page_profile_uri": "https://www.facebook.com/ToeicThayLong/",
    "page_profile_picture_url": "https://scontent.fhan14-2.fna.fbcdn.net/v/t39.35426-6/470185680_598783355885704_3569033089370598176_n.jpg?stp=dst-jpg_s60x60_tt6&_nc_cat=108&ccb=1-7&_nc_sid=c53f8f&_nc_ohc=cfu1NKUDF-0Q7kNvwEvLqkm&_nc_oc=Adk-KE_kWnqDZJsavRK7mP7RP3YUkw45C_vGuw0gKIHZWV4qYQgW6itM_tktYNra-3U&_nc_zt=14&_nc_ht=scontent.fhan14-2.fna&_nc_gid=aHbkyQBIBM_3jnFGNUwwVQ&oh=00_AfSb9d5eeE0S1US7XoVS5qJqUYO7we5qlew6zZwluKEfOg&oe=687C7158",
    "publisher_platform": [
      "FACEBOOK",
      "INSTAGRAM",
      "MESSENGER"
    ],
    "display_format": "CAROUSEL",
    "original_image_urls": [],
    "video_preview_image_url": null,
    "video_sd_url": null,
    "body_text": "Lộ trình 02 khoá học từ mất gốc đạt 550+ TOEIC\nCam kết đầu ra mục tiêu 550+ sau 5 tháng\n————————————\n👉 LỘ TRÌNH 02 khoá học bao gồm:\n✅ Giai đoạn 01: Dành cho các bạn mất gốc tiếng Anh \nLỚP TẬP SỰ:\n⚬ 3.200.000đ (25b)\n⚬ Phát triển kỹ năng nghe cơ bản\n⚬ Tích lũy từ vựng\n⚬ Học ngữ pháp cơ bản\nƯu đãi lớp học\n⚬ Miễn phí tài liệu \n⚬ Đăng ký và hoàn thành học phí trước 15.1.2025 giảm còn 2.800.000đ\n✅ Giai đoạn 02: Nếu các bạn có sẵn nền tảng có thể bắt đầu học từ giai đoạn 02\nLỚP TOEIC A:\n⚬ 27 buổi học (2 tháng 1 tuần)\n⚬ Hoàn thành toàn bộ phần nghe (part 1-2-3-4 )\n⚬ Hệ thống lại ngữ pháp cơ bản\n⚬ Làm quen với phần Reading cơ bản\n⚬ Sỹ số lớp học: 23-25 học viên\nƯu đãi lớp học\n⚬ Học phí gốc 3.900.000/27 buổi học (lớp học trực tiếp)\n⚬ Học phí đã bao gồm tài liệu toàn bộ khoá học.\n⚬ Với lớp Online thầy cô sẽ gửi file mềm giáo trình để chủ động photo ( học phí đã được giảm thêm 200k)\n⚬ Đăng ký và hoàn thành học phí trước 15.1.2025 giảm còn 3.400.000đ, đối với lớp Online là 3.200.000đ)\n\n————————————\n🎁 ƯU ĐÃI KHÁC VÀ HỖ TRỢ THI KHÁC \n​Thông tin chi tiết có tại: https://thaylongtoeic.com/ho-tro-thi/\nNhấn vào hashtag để xem thêm các bài viết review và bảng điểm của lớp bạn nhé 👉 #thaylongreview #thaylongbangdiem\n————————————\n👉 CÁCH THỨC ĐĂNG KÝ\nĐăng ký học trực tiếp trên website: https://thaylongtoeic.com/dangky/\nHoặc nhắn tin để nhận tư vấn thêm về thông tin khoá học và đăng ký\n————————————\n👉 ĐỊA CHỈ HỌC:\nCơ sở Hồ Tùng Mậu & Lê Đức Thọ: Số nhà 17B Ngõ 20 Hồ Tùng Mậu, Cầu Giấy, Hà Nội\nSố 9 Ngách 59 Ngõ 21 Lê Đức Thọ, Nam Từ Liêm, Hà Nội\nCơ sở Trần Đại Nghĩa: Tầng 4, 66 Trần Đại Nghĩa, Hai Bà Trưng, Hà Nội\nCơ Sở Hà Đông: Tầng 3 số 197 Trần Phú Hà Đông\nHotline + Zalo:\n0963352990 (Ms. Hà Linh)\n0961763990 (Ms. Thảo Đinh)",
    "cta_text": "Gửi tin nhắn",
    "start_date_readable": "14:00:00 23/06/2025",
    "end_date_readable": "14:00:00 14/07/2025",
    "duration_days": 21
  },
  {
    "is_active": true,
    "ad_archive_id": "3905682993077379",
    "collation_id": null,
    "collation_count": 0,
    "page_id": "425181617530046",
    "page_name": "Lớp Toeic Thầy Long",
    "page_profile_uri": "https://www.facebook.com/ToeicThayLong/",
    "page_profile_picture_url": "https://scontent.fhan14-1.fna.fbcdn.net/v/t39.35426-6/492008870_1310977066664553_7684121594598698367_n.jpg?stp=dst-jpg_s60x60_tt6&_nc_cat=101&ccb=1-7&_nc_sid=c53f8f&_nc_ohc=b32IjDSlzpEQ7kNvwFiDTGZ&_nc_oc=AdmZkdqX9wCc3m-z1w-6xnvmrYiszX7ikn8q1L_xCbGEOsvNkzzzrCDWLE3ILxNShQw&_nc_zt=14&_nc_ht=scontent.fhan14-1.fna&_nc_gid=aHbkyQBIBM_3jnFGNUwwVQ&oh=00_AfRL9M6K198cIgGWrGvd0Z3KyB1JxIX9BOpQntxiMSi1xw&oe=687C5E70",
    "publisher_platform": [
      "FACEBOOK",
      "INSTAGRAM",
      "MESSENGER"
    ],
    "display_format": "IMAGE",
    "original_image_urls": [
      "https://scontent.fhan14-5.fna.fbcdn.net/v/t39.35426-6/492209629_1787508055147259_7751361703801745998_n.jpg?_nc_cat=109&ccb=1-7&_nc_sid=c53f8f&_nc_ohc=YVzpIM9TS2YQ7kNvwFe4Dww&_nc_oc=AdnkpIwxPy7GqfJ_9axunjv01J0HehYDQt5b1a1W_zuvREzgf5NPE3M_7GqiGav770Q&_nc_zt=14&_nc_ht=scontent.fhan14-5.fna&_nc_gid=aHbkyQBIBM_3jnFGNUwwVQ&oh=00_AfS0ZzJVF0w-7H6HClr8ythYU4F2iMOERCSSCKfrt-cF5g&oe=687C544F"
    ],
    "video_preview_image_url": null,
    "video_sd_url": null,
    "body_text": "🎯 Chinh Phục TOEIC 4 Kỹ Năng Cùng Lớp TOEIC Thầy Long\n\nBạn đang tìm kiếm một khóa học TOEIC toàn diện giúp nâng cao cả 4 kỹ năng Nghe – Nói – Đọc – Viết? Hãy để Lớp TOEIC thầy Long đồng hành cùng bạn!\n\n🔹 Lộ trình tinh gọn, hiệu quả, phù hợp với mọi trình độ\n🔹 Website luyện đề mô phỏng 90% bài thi thật, giúp bạn làm quen với cấu trúc đề thi\n🔹 Cam kết đầu ra 4 kỹ năng, sẵn sàng đạt mục tiêu TOEIC mong muốn\n\n📩 Đăng ký ngay để được tư vấn và nhận tài liệu luyện thi miễn phí! 🚀",
    "cta_text": "Gửi tin nhắn",
    "start_date_readable": "14:00:00 12/06/2025",
    "end_date_readable": "14:00:00 13/07/2025",
    "duration_days": 31
  },
  {
    "is_active": true,
    "ad_archive_id": "24677585858498513",
    "collation_id": "4597958243767872",
    "collation_count": 1,
    "page_id": "425181617530046",
    "page_name": "Lớp Toeic Thầy Long",
    "page_profile_uri": "https://www.facebook.com/ToeicThayLong/",
    "page_profile_picture_url": "https://scontent.fhan14-2.fna.fbcdn.net/v/t39.35426-6/499041865_1311329843297172_1324280657016724934_n.jpg?stp=dst-jpg_s60x60_tt6&_nc_cat=108&ccb=1-7&_nc_sid=c53f8f&_nc_ohc=dXZpOgTT-gIQ7kNvwHzGv9j&_nc_oc=AdnrmiQgLW-Ki96BgurSLocRpyyBVcvC5R038J8dJIw1oGKPa79gZJrFQ931olrkJDk&_nc_zt=14&_nc_ht=scontent.fhan14-2.fna&_nc_gid=aHbkyQBIBM_3jnFGNUwwVQ&oh=00_AfSUdNf_8q8uQ1h-3H5U_gKRXpngrlzhexKk6FFjklreCg&oe=687C694A",
    "publisher_platform": [
      "FACEBOOK",
      "MESSENGER"
    ],
    "display_format": "VIDEO",
    "original_image_urls": [],
    "video_preview_image_url": null,
    "video_sd_url": null,
    "body_text": "Lộ trình 02 khoá học từ mất gốc đạt 550+\nCam kết đầu ra mục tiêu 550+ sau 5 tháng\n————————————\n👉 LỘ TRÌNH 02 khoá học bao gồm:\n✅ Giai đoạn 01: Dành cho các bạn mất gốc tiếng Anh\nLỚP TẬP SỰ:\n⚬ 3.200.000đ (25 buổi) (2,5 tháng)\n⚬ Phát triển kỹ năng nghe cơ bản\n⚬ Tích lũy từ vựng\n⚬ Học ngữ pháp cơ bản\nƯu đãi lớp học\n⚬ Miễn phí tài liệu\n⚬ Đăng ký và hoàn thành học phí trước khai giảng giảm còn 3.000.000đ\n✅ Giai đoạn 02: Nếu các bạn có sẵn nền tảng có thể bắt đầu học từ giai đoạn 02\nLỚP TOEIC A:\n⚬ 27 buổi học (2 tháng 1 tuần)\n⚬ Hoàn thành toàn bộ phần nghe (part 1-2-3-4 )\n⚬ Hệ thống lại ngữ pháp cơ bản\n⚬ Làm quen với phần Reading cơ bản\n⚬ Sỹ số lớp học: 23-25 học viên\n⚬ Học phí gốc 3.900.000/27 buổi học (lớp học trực tiếp)\nƯu đãi lớp học\n⚬ Học phí đã bao gồm tài liệu toàn bộ khoá học.\n⚬ Đăng ký và hoàn thành học phí trước khai giảng giảm còn 3.500.000đ\n✅ COMBO LỘ TRÌNH 550+: 6.000.000đ tiết kiệm 1.100.000đ so với đăng ký lẻ\n\n————————————\n🎁 ƯU ĐÃI KHÁC VÀ HỖ TRỢ THI KHÁC \n​Thông tin chi tiết có tại: https://thaylongtoeic.com/ho-tro-thi/\nNhấn vào hashtag để xem thêm các bài viết review và bảng điểm của lớp bạn nhé 👉 #thaylongreview #thaylongbangdiem\n————————————\n👉 CÁCH THỨC ĐĂNG KÝ\nĐăng ký học trực tiếp trên website: https://thaylongtoeic.com/dangky/\nHoặc nhắn tin để nhận tư vấn thêm về thông tin khoá học và đăng ký\n————————————\n👉 ĐỊA CHỈ HỌC:\nCơ sở Hồ Tùng Mậu & Lê Đức Thọ: Số nhà 17B Ngõ 20 Hồ Tùng Mậu, Cầu Giấy, Hà Nội\nSố 9 Ngách 59 Ngõ 21 Lê Đức Thọ, Nam Từ Liêm, Hà Nội\nCơ sở Trần Đại Nghĩa: Tầng 4, 66 Trần Đại Nghĩa, Hai Bà Trưng, Hà Nội\nCơ Sở Hà Đông: Tầng 3 số 197 Trần Phú Hà Đông\nHotline + Zalo:\n0963352990 \n0961763990",
    "cta_text": "Gửi tin nhắn",
    "start_date_readable": "14:00:00 12/06/2025",
    "end_date_readable": "14:00:00 12/07/2025",
    "duration_days": 30
  },
  {
    "is_active": true,
    "ad_archive_id": "614538394994415",
    "collation_id": "3409636275833995",
    "collation_count": 1,
    "page_id": "425181617530046",
    "page_name": "Lớp Toeic Thầy Long",
    "page_profile_uri": "https://www.facebook.com/ToeicThayLong/",
    "page_profile_picture_url": "https://scontent.fhan14-4.fna.fbcdn.net/v/t39.35426-6/498589844_4279064502380053_3233555941219221934_n.jpg?stp=dst-jpg_s60x60_tt6&_nc_cat=107&ccb=1-7&_nc_sid=c53f8f&_nc_ohc=6zs6kxJLrMYQ7kNvwGK-pN4&_nc_oc=AdkhOdWjyWZ6i-jDd7jDLZl5vnagxH5txDzdAzNljbMSP-W3xg_-gllTB8mr_lKhjeQ&_nc_zt=14&_nc_ht=scontent.fhan14-4.fna&_nc_gid=aHbkyQBIBM_3jnFGNUwwVQ&oh=00_AfTF5blgoLo0X7-93VkMP7NTJPzy2zDGnQOX-vk74TMZnw&oe=687C84FA",
    "publisher_platform": [
      "FACEBOOK",
      "MESSENGER"
    ],
    "display_format": "IMAGE",
    "original_image_urls": [
      "https://scontent.fhan14-2.fna.fbcdn.net/v/t39.35426-6/498589844_1168322815093815_5085226651304763235_n.jpg?_nc_cat=108&ccb=1-7&_nc_sid=c53f8f&_nc_ohc=vqRXB1U9hEgQ7kNvwGQft0v&_nc_oc=AdmswkCo-jEPBQ0qF_O8mwQ-ZJxshrwD_K4Uocn4FM897lWtbqfbtA31O29rZTDxsu8&_nc_zt=14&_nc_ht=scontent.fhan14-2.fna&_nc_gid=aHbkyQBIBM_3jnFGNUwwVQ&oh=00_AfTKoS0yVIhl9E_ZZZ7N8NE0qt_mkFHsSnIAXO87BG-rog&oe=687C677F"
    ],
    "video_preview_image_url": null,
    "video_sd_url": null,
    "body_text": "Lộ trình 02 khoá học từ mất gốc đạt 550+\nCam kết đầu ra mục tiêu 550+ sau 5 tháng\n————————————\n👉 LỘ TRÌNH 02 khoá học bao gồm:\n✅ Giai đoạn 01: Dành cho các bạn mất gốc tiếng Anh\nLỚP TẬP SỰ:\n⚬ 3.200.000đ (28 buổi) (2,5 tháng)\n⚬ Phát triển kỹ năng nghe cơ bản\n⚬ Tích lũy từ vựng\n⚬ Học ngữ pháp cơ bản\nƯu đãi lớp học\n⚬ Miễn phí tài liệu\n⚬ Đăng ký và hoàn thành học phí trước khai giảng giảm còn 3.000.000đ\n✅ Giai đoạn 02: Nếu các bạn có sẵn nền tảng có thể bắt đầu học từ giai đoạn 02\nLỚP TOEIC A:\n⚬ 27 buổi học (2 tháng 1 tuần)\n⚬ Hoàn thành toàn bộ phần nghe (part 1-2-3-4 )\n⚬ Hệ thống lại ngữ pháp cơ bản\n⚬ Làm quen với phần Reading cơ bản\n⚬ Sỹ số lớp học: 23-25 học viên\n⚬ Học phí gốc 3.900.000/27 buổi học (lớp học trực tiếp)\nƯu đãi lớp học\n⚬ Học phí đã bao gồm tài liệu toàn bộ khoá học.\n⚬ Đăng ký và hoàn thành học phí trước khai giảng giảm còn 3.500.000đ\n✅ COMBO LỘ TRÌNH 550+: 6.000.000đ tiết kiệm 1.100.000đ so với đăng ký lẻ\n\n————————————\n🎁 ƯU ĐÃI KHÁC VÀ HỖ TRỢ THI KHÁC \n​Thông tin chi tiết có tại: https://thaylongtoeic.com/ho-tro-thi/\nNhấn vào hashtag để xem thêm các bài viết review và bảng điểm của lớp bạn nhé 👉 #thaylongreview #thaylongbangdiem\n————————————\n👉 CÁCH THỨC ĐĂNG KÝ\nĐăng ký học trực tiếp trên website: https://thaylongtoeic.com/dangky/\nHoặc nhắn tin để nhận tư vấn thêm về thông tin khoá học và đăng ký\n————————————\n👉 ĐỊA CHỈ HỌC:\nCơ sở Hồ Tùng Mậu & Lê Đức Thọ: Số nhà 17B Ngõ 20 Hồ Tùng Mậu, Cầu Giấy, Hà Nội\nSố 9 Ngách 59 Ngõ 21 Lê Đức Thọ, Nam Từ Liêm, Hà Nội\nCơ sở Trần Đại Nghĩa: Tầng 4, 66 Trần Đại Nghĩa, Hai Bà Trưng, Hà Nội\nCơ Sở Hà Đông: Tầng 3 số 197 Trần Phú Hà Đông\nHotline + Zalo:\n0963352990 (Ms. Hà Linh)\n0961763990 (Ms. Thảo Đinh)",
    "cta_text": "Gửi tin nhắn",
    "start_date_readable": "14:00:00 12/06/2025",
    "end_date_readable": "14:00:00 13/07/2025",
    "duration_days": 31
  }
]